{
  "kind": "youtube#searchListResponse",
  "etag": "VvlbCKTIEzE_i3x9tv6U5sIBAJM",
  "nextPageToken": "CDIQAA",
  "regionCode": "US",
  "pageInfo": {
    "totalResults": 1316,
    "resultsPerPage": 50
  },
  "items": [
    {
      "kind": "youtube#searchResult",
      "etag": "IdchrdUfoV6xfuf9XKLGq7B-sjw",
      "id": {
        "kind": "youtube#video",
        "videoId": "PSKWTWru-3A"
      },
      "snippet": {
        "publishedAt": "2023-05-07T15:05:54Z",
        "channelId": "UC2MGuhIaOP6YLpUx106kTQw",
        "title": "Speed finals || Jakarta 2023",
        "description": "As the IFSC World Cup Series 2023 move on to Indonesia, the focus is truly on Speed with the discipline taking centre stage for a ...",
        "thumbnails": {
          "default": {
            "url": "https://i.ytimg.com/vi/PSKWTWru-3A/default.jpg",
            "width": 120,
            "height": 90
          },
          "medium": {
            "url": "https://i.ytimg.com/vi/PSKWTWru-3A/mqdefault.jpg",
            "width": 320,
            "height": 180
          },
          "high": {
            "url": "https://i.ytimg.com/vi/PSKWTWru-3A/hqdefault.jpg",
            "width": 480,
            "height": 360
          }
        },
        "channelTitle": "International Federation of Sport Climbing",
        "liveBroadcastContent": "none",
        "publishTime": "2023-05-07T15:05:54Z"
      }
    },
    {
      "kind": "youtube#searchResult",
      "etag": "yrmAZtJ-475hfU8P5nhWnMHa_i0",
      "id": {
        "kind": "youtube#video",
        "videoId": "iTDSiXLn0Xw"
      },
      "snippet": {
        "publishedAt": "2023-05-06T14:45:42Z",
        "channelId": "UC2MGuhIaOP6YLpUx106kTQw",
        "title": "Speed qualifications || Jakarta 2023",
        "description": "As the IFSC World Cup Series 2023 move on to Indonesia, the focus is truly on Speed with the discipline taking centre stage for a ...",
        "thumbnails": {
          "default": {
            "url": "https://i.ytimg.com/vi/iTDSiXLn0Xw/default.jpg",
            "width": 120,
            "height": 90
          },
          "medium": {
            "url": "https://i.ytimg.com/vi/iTDSiXLn0Xw/mqdefault.jpg",
            "width": 320,
            "height": 180
          },
          "high": {
            "url": "https://i.ytimg.com/vi/iTDSiXLn0Xw/hqdefault.jpg",
            "width": 480,
            "height": 360
          }
        },
        "channelTitle": "International Federation of Sport Climbing",
        "liveBroadcastContent": "none",
        "publishTime": "2023-05-06T14:45:42Z"
      }
    },
    {
      "kind": "youtube#searchResult",
      "etag": "_IR819IL7M9gk8cC8rWC3MWJ-gM",
      "id": {
        "kind": "youtube#video",
        "videoId": "ZcNQPzWeGK4"
      },
      "snippet": {
        "publishedAt": "2023-05-01T01:27:43Z",
        "channelId": "UC2MGuhIaOP6YLpUx106kTQw",
        "title": "Boulder finals highlights || Seoul 2023",
        "description": "The second IFSC World Cup event of the 2023 season takes place in Seoul, South Korea, from 28 to 30 April 2023 at the ...",
        "thumbnails": {
          "default": {
            "url": "https://i.ytimg.com/vi/ZcNQPzWeGK4/default.jpg",
            "width": 120,
            "height": 90
          },
          "medium": {
            "url": "https://i.ytimg.com/vi/ZcNQPzWeGK4/mqdefault.jpg",
            "width": 320,
            "height": 180
          },
          "high": {
            "url": "https://i.ytimg.com/vi/ZcNQPzWeGK4/hqdefault.jpg",
            "width": 480,
            "height": 360
          }
        },
        "channelTitle": "International Federation of Sport Climbing",
        "liveBroadcastContent": "none",
        "publishTime": "2023-05-01T01:27:43Z"
      }
    },
    {
      "kind": "youtube#searchResult",
      "etag": "xoUhPLtIh5-VnJqeHKvxs4YshUU",
      "id": {
        "kind": "youtube#video",
        "videoId": "4ZfaojD52K4"
      },
      "snippet": {
        "publishedAt": "2023-04-30T11:57:14Z",
        "channelId": "UC2MGuhIaOP6YLpUx106kTQw",
        "title": "Boulder finals || Seoul 2023",
        "description": "Featuring the inaugural competition of the Speed season, and the highly-anticipated second round of Boulder medal events, the ...",
        "thumbnails": {
          "default": {
            "url": "https://i.ytimg.com/vi/4ZfaojD52K4/default.jpg",
            "width": 120,
            "height": 90
          },
          "medium": {
            "url": "https://i.ytimg.com/vi/4ZfaojD52K4/mqdefault.jpg",
            "width": 320,
            "height": 180
          },
          "high": {
            "url": "https://i.ytimg.com/vi/4ZfaojD52K4/hqdefault.jpg",
            "width": 480,
            "height": 360
          }
        },
        "channelTitle": "International Federation of Sport Climbing",
        "liveBroadcastContent": "none",
        "publishTime": "2023-04-30T11:57:14Z"
      }
    },
    {
      "kind": "youtube#searchResult",
      "etag": "avlpYGs4n8TmRm7zSgGe00nPb4E",
      "id": {
        "kind": "youtube#video",
        "videoId": "hlS7_ZmEc-U"
      },
      "snippet": {
        "publishedAt": "2023-04-30T08:18:36Z",
        "channelId": "UC2MGuhIaOP6YLpUx106kTQw",
        "title": "Speed finals highlights || Seoul 2023",
        "description": "Featuring the inaugural competition of the Speed season, and the highly-anticipated second round of Boulder medal events, the ...",
        "thumbnails": {
          "default": {
            "url": "https://i.ytimg.com/vi/hlS7_ZmEc-U/default.jpg",
            "width": 120,
            "height": 90
          },
          "medium": {
            "url": "https://i.ytimg.com/vi/hlS7_ZmEc-U/mqdefault.jpg",
            "width": 320,
            "height": 180
          },
          "high": {
            "url": "https://i.ytimg.com/vi/hlS7_ZmEc-U/hqdefault.jpg",
            "width": 480,
            "height": 360
          }
        },
        "channelTitle": "International Federation of Sport Climbing",
        "liveBroadcastContent": "none",
        "publishTime": "2023-04-30T08:18:36Z"
      }
    },
    {
      "kind": "youtube#searchResult",
      "etag": "enByiL_6Ll97HIEt9sX3WJ7wCgg",
      "id": {
        "kind": "youtube#video",
        "videoId": "emrHdLsJTk4"
      },
      "snippet": {
        "publishedAt": "2023-04-30T07:48:24Z",
        "channelId": "UC2MGuhIaOP6YLpUx106kTQw",
        "title": "Men&#39;s Boulder qualification highlights || Seoul 2023",
        "description": "The second IFSC World Cup event of the 2023 season takes place in Seoul, South Korea, from 28 to 30 April 2023 at the ...",
        "thumbnails": {
          "default": {
            "url": "https://i.ytimg.com/vi/emrHdLsJTk4/default.jpg",
            "width": 120,
            "height": 90
          },
          "medium": {
            "url": "https://i.ytimg.com/vi/emrHdLsJTk4/mqdefault.jpg",
            "width": 320,
            "height": 180
          },
          "high": {
            "url": "https://i.ytimg.com/vi/emrHdLsJTk4/hqdefault.jpg",
            "width": 480,
            "height": 360
          }
        },
        "channelTitle": "International Federation of Sport Climbing",
        "liveBroadcastContent": "none",
        "publishTime": "2023-04-30T07:48:24Z"
      }
    },
    {
      "kind": "youtube#searchResult",
      "etag": "q-p_qHPDnjerOTbtCFE37iuzijM",
      "id": {
        "kind": "youtube#video",
        "videoId": "dZVTyhrrfao"
      },
      "snippet": {
        "publishedAt": "2023-04-30T03:00:43Z",
        "channelId": "UC2MGuhIaOP6YLpUx106kTQw",
        "title": "Women&#39;s Boulder qualification highlights || Seoul 2023",
        "description": "The second IFSC World Cup event of the 2023 season takes place in Seoul, South Korea, from 28 to 30 April 2023 at the ...",
        "thumbnails": {
          "default": {
            "url": "https://i.ytimg.com/vi/dZVTyhrrfao/default.jpg",
            "width": 120,
            "height": 90
          },
          "medium": {
            "url": "https://i.ytimg.com/vi/dZVTyhrrfao/mqdefault.jpg",
            "width": 320,
            "height": 180
          },
          "high": {
            "url": "https://i.ytimg.com/vi/dZVTyhrrfao/hqdefault.jpg",
            "width": 480,
            "height": 360
          }
        },
        "channelTitle": "International Federation of Sport Climbing",
        "liveBroadcastContent": "none",
        "publishTime": "2023-04-30T03:00:43Z"
      }
    },
    {
      "kind": "youtube#searchResult",
      "etag": "563dqTQ-wUKGDAkZTMIzqbv9Auo",
      "id": {
        "kind": "youtube#video",
        "videoId": "eIa6VYrfqX8"
      },
      "snippet": {
        "publishedAt": "2023-04-28T12:25:07Z",
        "channelId": "UC2MGuhIaOP6YLpUx106kTQw",
        "title": "Speed finals || Seoul 2023",
        "description": "Featuring the inaugural competition of the Speed season, and the highly-anticipated second round of Boulder medal events, the ...",
        "thumbnails": {
          "default": {
            "url": "https://i.ytimg.com/vi/eIa6VYrfqX8/default.jpg",
            "width": 120,
            "height": 90
          },
          "medium": {
            "url": "https://i.ytimg.com/vi/eIa6VYrfqX8/mqdefault.jpg",
            "width": 320,
            "height": 180
          },
          "high": {
            "url": "https://i.ytimg.com/vi/eIa6VYrfqX8/hqdefault.jpg",
            "width": 480,
            "height": 360
          }
        },
        "channelTitle": "International Federation of Sport Climbing",
        "liveBroadcastContent": "none",
        "publishTime": "2023-04-28T12:25:07Z"
      }
    },
    {
      "kind": "youtube#searchResult",
      "etag": "8j2PCt6P6vVcEAq0BiQzLZksWOY",
      "id": {
        "kind": "youtube#video",
        "videoId": "_g-5mDjwO0I"
      },
      "snippet": {
        "publishedAt": "2023-04-28T06:05:45Z",
        "channelId": "UC2MGuhIaOP6YLpUx106kTQw",
        "title": "It&#39;s happened! 🤯A sub-5 at the IFSC World Cup in Seoul for Veddriq Leonardo 🇮🇩",
        "description": "More news: https://bit.ly/3ivwb9v Subscribe: https://bit.ly/3oveCdv.",
        "thumbnails": {
          "default": {
            "url": "https://i.ytimg.com/vi/_g-5mDjwO0I/default.jpg",
            "width": 120,
            "height": 90
          },
          "medium": {
            "url": "https://i.ytimg.com/vi/_g-5mDjwO0I/mqdefault.jpg",
            "width": 320,
            "height": 180
          },
          "high": {
            "url": "https://i.ytimg.com/vi/_g-5mDjwO0I/hqdefault.jpg",
            "width": 480,
            "height": 360
          }
        },
        "channelTitle": "International Federation of Sport Climbing",
        "liveBroadcastContent": "none",
        "publishTime": "2023-04-28T06:05:45Z"
      }
    },
    {
      "kind": "youtube#searchResult",
      "etag": "idHhnUH0e7pOZLHkHsu2awLDrLM",
      "id": {
        "kind": "youtube#video",
        "videoId": "mC1RhpB4uuQ"
      },
      "snippet": {
        "publishedAt": "2023-04-28T06:02:47Z",
        "channelId": "UC2MGuhIaOP6YLpUx106kTQw",
        "title": "Speed qualifications || Seoul 2023",
        "description": "Featuring the inaugural competition of the Speed season, and the highly-anticipated second round of Boulder medal events, the ...",
        "thumbnails": {
          "default": {
            "url": "https://i.ytimg.com/vi/mC1RhpB4uuQ/default.jpg",
            "width": 120,
            "height": 90
          },
          "medium": {
            "url": "https://i.ytimg.com/vi/mC1RhpB4uuQ/mqdefault.jpg",
            "width": 320,
            "height": 180
          },
          "high": {
            "url": "https://i.ytimg.com/vi/mC1RhpB4uuQ/hqdefault.jpg",
            "width": 480,
            "height": 360
          }
        },
        "channelTitle": "International Federation of Sport Climbing",
        "liveBroadcastContent": "none",
        "publishTime": "2023-04-28T06:02:47Z"
      }
    },
    {
      "kind": "youtube#searchResult",
      "etag": "_tSWjIRE3OOYov9Cl941a_ZTL1w",
      "id": {
        "kind": "youtube#video",
        "videoId": "UiJ5rYzEm7Y"
      },
      "snippet": {
        "publishedAt": "2023-04-23T23:26:37Z",
        "channelId": "UC2MGuhIaOP6YLpUx106kTQw",
        "title": "Mejdi Schalck’s top on M1 turned out to be his golden moment at the end of a hard-fought final!",
        "description": "More news: https://bit.ly/3ivwb9v ✍️ Subscribe: https://bit.ly/3oveCdv IFSC website: https://www.ifsc-climbing.org/ Rankings: ...",
        "thumbnails": {
          "default": {
            "url": "https://i.ytimg.com/vi/UiJ5rYzEm7Y/default.jpg",
            "width": 120,
            "height": 90
          },
          "medium": {
            "url": "https://i.ytimg.com/vi/UiJ5rYzEm7Y/mqdefault.jpg",
            "width": 320,
            "height": 180
          },
          "high": {
            "url": "https://i.ytimg.com/vi/UiJ5rYzEm7Y/hqdefault.jpg",
            "width": 480,
            "height": 360
          }
        },
        "channelTitle": "International Federation of Sport Climbing",
        "liveBroadcastContent": "none",
        "publishTime": "2023-04-23T23:26:37Z"
      }
    },
    {
      "kind": "youtube#searchResult",
      "etag": "DzgSMOJlMrqUYFWz6QcrLE9LWps",
      "id": {
        "kind": "youtube#video",
        "videoId": "Zij5481HJl4"
      },
      "snippet": {
        "publishedAt": "2023-04-23T15:59:35Z",
        "channelId": "UC2MGuhIaOP6YLpUx106kTQw",
        "title": "Men&#39;s Boulder final highlights || Hachioji 2023",
        "description": "Experienced climbers Chon Jongwon and Fujii Kokoro faced a pack of four promising young talents, led by France's Paul Jenft ...",
        "thumbnails": {
          "default": {
            "url": "https://i.ytimg.com/vi/Zij5481HJl4/default.jpg",
            "width": 120,
            "height": 90
          },
          "medium": {
            "url": "https://i.ytimg.com/vi/Zij5481HJl4/mqdefault.jpg",
            "width": 320,
            "height": 180
          },
          "high": {
            "url": "https://i.ytimg.com/vi/Zij5481HJl4/hqdefault.jpg",
            "width": 480,
            "height": 360
          }
        },
        "channelTitle": "International Federation of Sport Climbing",
        "liveBroadcastContent": "none",
        "publishTime": "2023-04-23T15:59:35Z"
      }
    },
    {
      "kind": "youtube#searchResult",
      "etag": "cG56eB7VIbTMk6EJ_8JnCJp9NMQ",
      "id": {
        "kind": "youtube#video",
        "videoId": "JX_-Ab7-IPY"
      },
      "snippet": {
        "publishedAt": "2023-04-23T12:17:36Z",
        "channelId": "UC2MGuhIaOP6YLpUx106kTQw",
        "title": "Men&#39;s Boulder final || Hachioji 2023",
        "description": "The IFSC World Cup Series 2023 kicked off in Hachioji, Japan, from 21 to 23 April. A total of 171 climbers gathered at the Esforta ...",
        "thumbnails": {
          "default": {
            "url": "https://i.ytimg.com/vi/JX_-Ab7-IPY/default.jpg",
            "width": 120,
            "height": 90
          },
          "medium": {
            "url": "https://i.ytimg.com/vi/JX_-Ab7-IPY/mqdefault.jpg",
            "width": 320,
            "height": 180
          },
          "high": {
            "url": "https://i.ytimg.com/vi/JX_-Ab7-IPY/hqdefault.jpg",
            "width": 480,
            "height": 360
          }
        },
        "channelTitle": "International Federation of Sport Climbing",
        "liveBroadcastContent": "none",
        "publishTime": "2023-04-23T12:17:36Z"
      }
    },
    {
      "kind": "youtube#searchResult",
      "etag": "l4vy_QRxRKS-z-MT2MriY0vQ7Qs",
      "id": {
        "kind": "youtube#video",
        "videoId": "VqUSLFSNOgM"
      },
      "snippet": {
        "publishedAt": "2023-04-23T05:24:14Z",
        "channelId": "UC2MGuhIaOP6YLpUx106kTQw",
        "title": "Only one way for Brooke Raboutou 🇺🇸  to secure her first-ever World Cup gold medal: topping W4!",
        "description": "More news: https://bit.ly/3ivwb9v ✍️ Subscribe: https://bit.ly/3oveCdv IFSC website: https://www.ifsc-climbing.org/ Rankings: ...",
        "thumbnails": {
          "default": {
            "url": "https://i.ytimg.com/vi/VqUSLFSNOgM/default.jpg",
            "width": 120,
            "height": 90
          },
          "medium": {
            "url": "https://i.ytimg.com/vi/VqUSLFSNOgM/mqdefault.jpg",
            "width": 320,
            "height": 180
          },
          "high": {
            "url": "https://i.ytimg.com/vi/VqUSLFSNOgM/hqdefault.jpg",
            "width": 480,
            "height": 360
          }
        },
        "channelTitle": "International Federation of Sport Climbing",
        "liveBroadcastContent": "none",
        "publishTime": "2023-04-23T05:24:14Z"
      }
    },
    {
      "kind": "youtube#searchResult",
      "etag": "wYEtLNqsyt2_BCuxgWgnFb4TteM",
      "id": {
        "kind": "youtube#video",
        "videoId": "_D1hGBIEdQw"
      },
      "snippet": {
        "publishedAt": "2023-04-23T04:36:52Z",
        "channelId": "UC2MGuhIaOP6YLpUx106kTQw",
        "title": "Men&#39;s Boulder semi-final || Hachioji 2023",
        "description": "The IFSC World Cup Series 2023 kicked off in Hachioji, Japan, from 21 to 23 April. A total of 171 climbers gathered at the Esforta ...",
        "thumbnails": {
          "default": {
            "url": "https://i.ytimg.com/vi/_D1hGBIEdQw/default.jpg",
            "width": 120,
            "height": 90
          },
          "medium": {
            "url": "https://i.ytimg.com/vi/_D1hGBIEdQw/mqdefault.jpg",
            "width": 320,
            "height": 180
          },
          "high": {
            "url": "https://i.ytimg.com/vi/_D1hGBIEdQw/hqdefault.jpg",
            "width": 480,
            "height": 360
          }
        },
        "channelTitle": "International Federation of Sport Climbing",
        "liveBroadcastContent": "none",
        "publishTime": "2023-04-23T04:36:52Z"
      }
    },
    {
      "kind": "youtube#searchResult",
      "etag": "xNeVHRBHKAlHI1VGW2OSOQQzzcA",
      "id": {
        "kind": "youtube#video",
        "videoId": "Cy6pZWQuGJY"
      },
      "snippet": {
        "publishedAt": "2023-04-22T15:41:27Z",
        "channelId": "UC2MGuhIaOP6YLpUx106kTQw",
        "title": "Women&#39;s Boulder final highlights || Hachioji 2023",
        "description": "A field of six climbers, from six different countries, with an overall tally of zero World Cup gold medals, battled it out for the first ...",
        "thumbnails": {
          "default": {
            "url": "https://i.ytimg.com/vi/Cy6pZWQuGJY/default.jpg",
            "width": 120,
            "height": 90
          },
          "medium": {
            "url": "https://i.ytimg.com/vi/Cy6pZWQuGJY/mqdefault.jpg",
            "width": 320,
            "height": 180
          },
          "high": {
            "url": "https://i.ytimg.com/vi/Cy6pZWQuGJY/hqdefault.jpg",
            "width": 480,
            "height": 360
          }
        },
        "channelTitle": "International Federation of Sport Climbing",
        "liveBroadcastContent": "none",
        "publishTime": "2023-04-22T15:41:27Z"
      }
    },
    {
      "kind": "youtube#searchResult",
      "etag": "yb4I01nT1izG1WhSFKyzDGvAC78",
      "id": {
        "kind": "youtube#video",
        "videoId": "eNR77KOXi20"
      },
      "snippet": {
        "publishedAt": "2023-04-22T13:14:46Z",
        "channelId": "UC2MGuhIaOP6YLpUx106kTQw",
        "title": "Women&#39;s Boulder final || Hachioji 2023",
        "description": "The IFSC World Cup Series 2023 kicked off in Hachioji, Japan, from 21 to 23 April. A total of 171 climbers gathered at the Esforta ...",
        "thumbnails": {
          "default": {
            "url": "https://i.ytimg.com/vi/eNR77KOXi20/default.jpg",
            "width": 120,
            "height": 90
          },
          "medium": {
            "url": "https://i.ytimg.com/vi/eNR77KOXi20/mqdefault.jpg",
            "width": 320,
            "height": 180
          },
          "high": {
            "url": "https://i.ytimg.com/vi/eNR77KOXi20/hqdefault.jpg",
            "width": 480,
            "height": 360
          }
        },
        "channelTitle": "International Federation of Sport Climbing",
        "liveBroadcastContent": "none",
        "publishTime": "2023-04-22T13:14:46Z"
      }
    },
    {
      "kind": "youtube#searchResult",
      "etag": "BxJ10Xb7ifRPDXLU1gFdJ0uduf4",
      "id": {
        "kind": "youtube#video",
        "videoId": "kuE-qhRq7Fk"
      },
      "snippet": {
        "publishedAt": "2023-04-22T06:42:42Z",
        "channelId": "UC2MGuhIaOP6YLpUx106kTQw",
        "title": "Women&#39;s Boulder semi-final || Hachioji 2023",
        "description": "The IFSC World Cup Series 2023 kicked off in Hachioji, Japan, from 21 to 23 April. A total of 171 climbers gathered at the Esforta ...",
        "thumbnails": {
          "default": {
            "url": "https://i.ytimg.com/vi/kuE-qhRq7Fk/default.jpg",
            "width": 120,
            "height": 90
          },
          "medium": {
            "url": "https://i.ytimg.com/vi/kuE-qhRq7Fk/mqdefault.jpg",
            "width": 320,
            "height": 180
          },
          "high": {
            "url": "https://i.ytimg.com/vi/kuE-qhRq7Fk/hqdefault.jpg",
            "width": 480,
            "height": 360
          }
        },
        "channelTitle": "International Federation of Sport Climbing",
        "liveBroadcastContent": "none",
        "publishTime": "2023-04-22T06:42:42Z"
      }
    },
    {
      "kind": "youtube#searchResult",
      "etag": "fZBOAmTV9zoeK3qgeKXxVhF0Zcg",
      "id": {
        "kind": "youtube#video",
        "videoId": "MQeQs6K_T5g"
      },
      "snippet": {
        "publishedAt": "2023-04-21T14:35:41Z",
        "channelId": "UC2MGuhIaOP6YLpUx106kTQw",
        "title": "Qualifications highlights || Hachioji 2023",
        "description": "More news: https://bit.ly/3ivwb9v Subscribe: https://bit.ly/3oveCdv.",
        "thumbnails": {
          "default": {
            "url": "https://i.ytimg.com/vi/MQeQs6K_T5g/default.jpg",
            "width": 120,
            "height": 90
          },
          "medium": {
            "url": "https://i.ytimg.com/vi/MQeQs6K_T5g/mqdefault.jpg",
            "width": 320,
            "height": 180
          },
          "high": {
            "url": "https://i.ytimg.com/vi/MQeQs6K_T5g/hqdefault.jpg",
            "width": 480,
            "height": 360
          }
        },
        "channelTitle": "International Federation of Sport Climbing",
        "liveBroadcastContent": "none",
        "publishTime": "2023-04-21T14:35:41Z"
      }
    },
    {
      "kind": "youtube#searchResult",
      "etag": "IXE2L_rEybjv0rDDkLVUW9SdqLc",
      "id": {
        "kind": "youtube#video",
        "videoId": "vT8UFPP3I-g"
      },
      "snippet": {
        "publishedAt": "2023-04-20T07:19:58Z",
        "channelId": "UC2MGuhIaOP6YLpUx106kTQw",
        "title": "IFSC Routesetter Olga Niemiec presents one of the coolest holds you will see on the wall in Hachioji",
        "description": "",
        "thumbnails": {
          "default": {
            "url": "https://i.ytimg.com/vi/vT8UFPP3I-g/default.jpg",
            "width": 120,
            "height": 90
          },
          "medium": {
            "url": "https://i.ytimg.com/vi/vT8UFPP3I-g/mqdefault.jpg",
            "width": 320,
            "height": 180
          },
          "high": {
            "url": "https://i.ytimg.com/vi/vT8UFPP3I-g/hqdefault.jpg",
            "width": 480,
            "height": 360
          }
        },
        "channelTitle": "International Federation of Sport Climbing",
        "liveBroadcastContent": "none",
        "publishTime": "2023-04-20T07:19:58Z"
      }
    },
    {
      "kind": "youtube#searchResult",
      "etag": "jZvWiKu1-PN4ka9PL0RFSAlry30",
      "id": {
        "kind": "youtube#video",
        "videoId": "Lovh9GDV6AI"
      },
      "snippet": {
        "publishedAt": "2022-10-23T11:58:15Z",
        "channelId": "UC2MGuhIaOP6YLpUx106kTQw",
        "title": "Women&#39;s Boulder &amp; Lead final highlights || IFSC World Cup Morioka, Iwate 2022",
        "description": "In the third outing of the Olympic Games Paris 2024 format, 67 climbers from across the globe will fight it out for a chance to stand ...",
        "thumbnails": {
          "default": {
            "url": "https://i.ytimg.com/vi/Lovh9GDV6AI/default.jpg",
            "width": 120,
            "height": 90
          },
          "medium": {
            "url": "https://i.ytimg.com/vi/Lovh9GDV6AI/mqdefault.jpg",
            "width": 320,
            "height": 180
          },
          "high": {
            "url": "https://i.ytimg.com/vi/Lovh9GDV6AI/hqdefault.jpg",
            "width": 480,
            "height": 360
          }
        },
        "channelTitle": "International Federation of Sport Climbing",
        "liveBroadcastContent": "none",
        "publishTime": "2022-10-23T11:58:15Z"
      }
    },
    {
      "kind": "youtube#searchResult",
      "etag": "pb_DPG-Y7kG7fcHSicv7fY3E5RQ",
      "id": {
        "kind": "youtube#video",
        "videoId": "Du-tUzWZ65A"
      },
      "snippet": {
        "publishedAt": "2022-10-22T09:08:56Z",
        "channelId": "UC2MGuhIaOP6YLpUx106kTQw",
        "title": "Women&#39;s Boulder &amp; Lead final || IFSC World Cup Morioka, Iwate 2022",
        "description": "In the third outing of the Olympic Games Paris 2024 format, 78 climbers from across the globe will fight it out for a chance to stand ...",
        "thumbnails": {
          "default": {
            "url": "https://i.ytimg.com/vi/Du-tUzWZ65A/default.jpg",
            "width": 120,
            "height": 90
          },
          "medium": {
            "url": "https://i.ytimg.com/vi/Du-tUzWZ65A/mqdefault.jpg",
            "width": 320,
            "height": 180
          },
          "high": {
            "url": "https://i.ytimg.com/vi/Du-tUzWZ65A/hqdefault.jpg",
            "width": 480,
            "height": 360
          }
        },
        "channelTitle": "International Federation of Sport Climbing",
        "liveBroadcastContent": "none",
        "publishTime": "2022-10-22T09:08:56Z"
      }
    },
    {
      "kind": "youtube#searchResult",
      "etag": "ZvdaVJzOxNJIioiLf3KhaMNc2Cw",
      "id": {
        "kind": "youtube#video",
        "videoId": "OZCyThu0EpQ"
      },
      "snippet": {
        "publishedAt": "2022-10-22T04:38:10Z",
        "channelId": "UC2MGuhIaOP6YLpUx106kTQw",
        "title": "Men&#39;s Boulder &amp; Lead final highlights || IFSC World Cup Morioka, Iwate 2022",
        "description": "In the third outing of the Olympic Games Paris 2024 format, 67 climbers from across the globe will fight it out for a chance to stand ...",
        "thumbnails": {
          "default": {
            "url": "https://i.ytimg.com/vi/OZCyThu0EpQ/default.jpg",
            "width": 120,
            "height": 90
          },
          "medium": {
            "url": "https://i.ytimg.com/vi/OZCyThu0EpQ/mqdefault.jpg",
            "width": 320,
            "height": 180
          },
          "high": {
            "url": "https://i.ytimg.com/vi/OZCyThu0EpQ/hqdefault.jpg",
            "width": 480,
            "height": 360
          }
        },
        "channelTitle": "International Federation of Sport Climbing",
        "liveBroadcastContent": "none",
        "publishTime": "2022-10-22T04:38:10Z"
      }
    },
    {
      "kind": "youtube#searchResult",
      "etag": "k9iIJgJH-o8DgauXDRsmsOPGOJc",
      "id": {
        "kind": "youtube#video",
        "videoId": "LFvgpPoYlTA"
      },
      "snippet": {
        "publishedAt": "2022-10-21T17:15:15Z",
        "channelId": "UC2MGuhIaOP6YLpUx106kTQw",
        "title": "Boulder &amp; Lead semi-finals || IFSC World Cup Morioka, Iwate 2022",
        "description": "In the third outing of the Olympic Games Paris 2024 format, 67 climbers from across the globe will fight it out for a chance to stand ...",
        "thumbnails": {
          "default": {
            "url": "https://i.ytimg.com/vi/LFvgpPoYlTA/default.jpg",
            "width": 120,
            "height": 90
          },
          "medium": {
            "url": "https://i.ytimg.com/vi/LFvgpPoYlTA/mqdefault.jpg",
            "width": 320,
            "height": 180
          },
          "high": {
            "url": "https://i.ytimg.com/vi/LFvgpPoYlTA/hqdefault.jpg",
            "width": 480,
            "height": 360
          }
        },
        "channelTitle": "International Federation of Sport Climbing",
        "liveBroadcastContent": "none",
        "publishTime": "2022-10-21T17:15:15Z"
      }
    },
    {
      "kind": "youtube#searchResult",
      "etag": "RLn6D0McDW9c0Z5OYgmtc2BSj-c",
      "id": {
        "kind": "youtube#video",
        "videoId": "t50471uh7bM"
      },
      "snippet": {
        "publishedAt": "2022-10-21T12:41:22Z",
        "channelId": "UC2MGuhIaOP6YLpUx106kTQw",
        "title": "Men&#39;s Boulder &amp; Lead final || IFSC World Cup Morioka, Iwate 2022",
        "description": "In the third outing of the Olympic Games Paris 2024 format, 78 climbers from across the globe will fight it out for a chance to stand ...",
        "thumbnails": {
          "default": {
            "url": "https://i.ytimg.com/vi/t50471uh7bM/default.jpg",
            "width": 120,
            "height": 90
          },
          "medium": {
            "url": "https://i.ytimg.com/vi/t50471uh7bM/mqdefault.jpg",
            "width": 320,
            "height": 180
          },
          "high": {
            "url": "https://i.ytimg.com/vi/t50471uh7bM/hqdefault.jpg",
            "width": 480,
            "height": 360
          }
        },
        "channelTitle": "International Federation of Sport Climbing",
        "liveBroadcastContent": "none",
        "publishTime": "2022-10-21T12:41:22Z"
      }
    },
    {
      "kind": "youtube#searchResult",
      "etag": "-fVY-pQ1KKJ636A5s1yfAU9hpOo",
      "id": {
        "kind": "youtube#video",
        "videoId": "A1hyEmuJXMo"
      },
      "snippet": {
        "publishedAt": "2022-10-21T02:36:32Z",
        "channelId": "UC2MGuhIaOP6YLpUx106kTQw",
        "title": "Boulder &amp; Lead semi-finals || IFSC World Cup Morioka, Iwate 2022",
        "description": "In the third outing of the Olympic Games Paris 2024 format, 78 climbers from across the globe will fight it out for a chance to stand ...",
        "thumbnails": {
          "default": {
            "url": "https://i.ytimg.com/vi/A1hyEmuJXMo/default.jpg",
            "width": 120,
            "height": 90
          },
          "medium": {
            "url": "https://i.ytimg.com/vi/A1hyEmuJXMo/mqdefault.jpg",
            "width": 320,
            "height": 180
          },
          "high": {
            "url": "https://i.ytimg.com/vi/A1hyEmuJXMo/hqdefault.jpg",
            "width": 480,
            "height": 360
          }
        },
        "channelTitle": "International Federation of Sport Climbing",
        "liveBroadcastContent": "none",
        "publishTime": "2022-10-21T02:36:32Z"
      }
    },
    {
      "kind": "youtube#searchResult",
      "etag": "CYs-cGORBhzbNAupU2m2Qs_LZ7k",
      "id": {
        "kind": "youtube#video",
        "videoId": "ZWPNYtY4nSc"
      },
      "snippet": {
        "publishedAt": "2022-10-20T11:44:13Z",
        "channelId": "UC2MGuhIaOP6YLpUx106kTQw",
        "title": "Boulder &amp; Lead qualifications highlights || IFSC World Cup Morioka, Iwate 2022",
        "description": "In the third outing of the Olympic Games Paris 2024 format, 67 climbers from across the globe will fight it out for a chance to stand ...",
        "thumbnails": {
          "default": {
            "url": "https://i.ytimg.com/vi/ZWPNYtY4nSc/default.jpg",
            "width": 120,
            "height": 90
          },
          "medium": {
            "url": "https://i.ytimg.com/vi/ZWPNYtY4nSc/mqdefault.jpg",
            "width": 320,
            "height": 180
          },
          "high": {
            "url": "https://i.ytimg.com/vi/ZWPNYtY4nSc/hqdefault.jpg",
            "width": 480,
            "height": 360
          }
        },
        "channelTitle": "International Federation of Sport Climbing",
        "liveBroadcastContent": "none",
        "publishTime": "2022-10-20T11:44:13Z"
      }
    },
    {
      "kind": "youtube#searchResult",
      "etag": "8ODk8kBWkioGEZltVPuarbqvxE0",
      "id": {
        "kind": "youtube#video",
        "videoId": "cFECr4hCFKo"
      },
      "snippet": {
        "publishedAt": "2022-10-16T08:53:24Z",
        "channelId": "UC2MGuhIaOP6YLpUx106kTQw",
        "title": "Men&#39;s Boulder &amp; Lead final || IFSC Asian Championships Seoul 2022",
        "description": "More news: https://bit.ly/3ivwb9v Subscribe: https://bit.ly/3oveCdv.",
        "thumbnails": {
          "default": {
            "url": "https://i.ytimg.com/vi/cFECr4hCFKo/default.jpg",
            "width": 120,
            "height": 90
          },
          "medium": {
            "url": "https://i.ytimg.com/vi/cFECr4hCFKo/mqdefault.jpg",
            "width": 320,
            "height": 180
          },
          "high": {
            "url": "https://i.ytimg.com/vi/cFECr4hCFKo/hqdefault.jpg",
            "width": 480,
            "height": 360
          }
        },
        "channelTitle": "International Federation of Sport Climbing",
        "liveBroadcastContent": "none",
        "publishTime": "2022-10-16T08:53:24Z"
      }
    },
    {
      "kind": "youtube#searchResult",
      "etag": "Y_Xwau3I2XiNhK96b5t9eCR3SsM",
      "id": {
        "kind": "youtube#video",
        "videoId": "fFzw63dP1YM"
      },
      "snippet": {
        "publishedAt": "2022-10-16T04:17:39Z",
        "channelId": "UC2MGuhIaOP6YLpUx106kTQw",
        "title": "Women&#39;s Boulder &amp; Lead final || IFSC Asian Championships Seoul 2022",
        "description": "More news: https://bit.ly/3ivwb9v Subscribe: https://bit.ly/3oveCdv.",
        "thumbnails": {
          "default": {
            "url": "https://i.ytimg.com/vi/fFzw63dP1YM/default.jpg",
            "width": 120,
            "height": 90
          },
          "medium": {
            "url": "https://i.ytimg.com/vi/fFzw63dP1YM/mqdefault.jpg",
            "width": 320,
            "height": 180
          },
          "high": {
            "url": "https://i.ytimg.com/vi/fFzw63dP1YM/hqdefault.jpg",
            "width": 480,
            "height": 360
          }
        },
        "channelTitle": "International Federation of Sport Climbing",
        "liveBroadcastContent": "none",
        "publishTime": "2022-10-16T04:17:39Z"
      }
    },
    {
      "kind": "youtube#searchResult",
      "etag": "HDBLW5OlJkYLtoyS3mm4TTlwOtc",
      "id": {
        "kind": "youtube#video",
        "videoId": "DgNoSFYaDdE"
      },
      "snippet": {
        "publishedAt": "2022-09-26T18:02:50Z",
        "channelId": "UC2MGuhIaOP6YLpUx106kTQw",
        "title": "Lead finals highlights || Jakarta 2022",
        "description": "The International Federation of Sport Climbing (IFSC) Lead and Speed World Cup 2022 season will come to a close in Jakarta, ...",
        "thumbnails": {
          "default": {
            "url": "https://i.ytimg.com/vi/DgNoSFYaDdE/default.jpg",
            "width": 120,
            "height": 90
          },
          "medium": {
            "url": "https://i.ytimg.com/vi/DgNoSFYaDdE/mqdefault.jpg",
            "width": 320,
            "height": 180
          },
          "high": {
            "url": "https://i.ytimg.com/vi/DgNoSFYaDdE/hqdefault.jpg",
            "width": 480,
            "height": 360
          }
        },
        "channelTitle": "International Federation of Sport Climbing",
        "liveBroadcastContent": "none",
        "publishTime": "2022-09-26T18:02:50Z"
      }
    },
    {
      "kind": "youtube#searchResult",
      "etag": "1cAFAZ_9QIA8wHJDzLT8XJGWydM",
      "id": {
        "kind": "youtube#video",
        "videoId": "xlpFynDe144"
      },
      "snippet": {
        "publishedAt": "2022-09-26T14:48:27Z",
        "channelId": "UC2MGuhIaOP6YLpUx106kTQw",
        "title": "Lead finals || Jakarta 2022",
        "description": "The International Federation of Sport Climbing (IFSC) Lead and Speed World Cup 2022 season will come to a close in Jakarta, ...",
        "thumbnails": {
          "default": {
            "url": "https://i.ytimg.com/vi/xlpFynDe144/default.jpg",
            "width": 120,
            "height": 90
          },
          "medium": {
            "url": "https://i.ytimg.com/vi/xlpFynDe144/mqdefault.jpg",
            "width": 320,
            "height": 180
          },
          "high": {
            "url": "https://i.ytimg.com/vi/xlpFynDe144/hqdefault.jpg",
            "width": 480,
            "height": 360
          }
        },
        "channelTitle": "International Federation of Sport Climbing",
        "liveBroadcastContent": "none",
        "publishTime": "2022-09-26T14:48:27Z"
      }
    },
    {
      "kind": "youtube#searchResult",
      "etag": "gsjctBzR8D0R7ROCIJ0zaStQ4pQ",
      "id": {
        "kind": "youtube#video",
        "videoId": "ZPVxdFFLXl8"
      },
      "snippet": {
        "publishedAt": "2022-09-26T07:46:36Z",
        "channelId": "UC2MGuhIaOP6YLpUx106kTQw",
        "title": "Lead semi-finals || Jakarta 2022",
        "description": "The International Federation of Sport Climbing (IFSC) Lead and Speed World Cup 2022 season will come to a close in Jakarta, ...",
        "thumbnails": {
          "default": {
            "url": "https://i.ytimg.com/vi/ZPVxdFFLXl8/default.jpg",
            "width": 120,
            "height": 90
          },
          "medium": {
            "url": "https://i.ytimg.com/vi/ZPVxdFFLXl8/mqdefault.jpg",
            "width": 320,
            "height": 180
          },
          "high": {
            "url": "https://i.ytimg.com/vi/ZPVxdFFLXl8/hqdefault.jpg",
            "width": 480,
            "height": 360
          }
        },
        "channelTitle": "International Federation of Sport Climbing",
        "liveBroadcastContent": "none",
        "publishTime": "2022-09-26T07:46:36Z"
      }
    },
    {
      "kind": "youtube#searchResult",
      "etag": "zNQwgHnVaeL7Q4rA1p6IXwv7wAs",
      "id": {
        "kind": "youtube#video",
        "videoId": "HCC5iiLG9qs"
      },
      "snippet": {
        "publishedAt": "2022-09-26T03:55:38Z",
        "channelId": "UC2MGuhIaOP6YLpUx106kTQw",
        "title": "Lead qualifications highlights || Jakarta 2022",
        "description": "The International Federation of Sport Climbing (IFSC) Lead and Speed World Cup 2022 season will come to a close in Jakarta, ...",
        "thumbnails": {
          "default": {
            "url": "https://i.ytimg.com/vi/HCC5iiLG9qs/default.jpg",
            "width": 120,
            "height": 90
          },
          "medium": {
            "url": "https://i.ytimg.com/vi/HCC5iiLG9qs/mqdefault.jpg",
            "width": 320,
            "height": 180
          },
          "high": {
            "url": "https://i.ytimg.com/vi/HCC5iiLG9qs/hqdefault.jpg",
            "width": 480,
            "height": 360
          }
        },
        "channelTitle": "International Federation of Sport Climbing",
        "liveBroadcastContent": "none",
        "publishTime": "2022-09-26T03:55:38Z"
      }
    },
    {
      "kind": "youtube#searchResult",
      "etag": "yiEVB1LZabD4P0gcDKelaGfiu0I",
      "id": {
        "kind": "youtube#video",
        "videoId": "UVoh1lnyB7U"
      },
      "snippet": {
        "publishedAt": "2022-09-25T01:46:31Z",
        "channelId": "UC2MGuhIaOP6YLpUx106kTQw",
        "title": "Speed finals highlights || Jakarta 2022",
        "description": "The International Federation of Sport Climbing (IFSC) Lead and Speed World Cup 2022 season will come to a close in Jakarta, ...",
        "thumbnails": {
          "default": {
            "url": "https://i.ytimg.com/vi/UVoh1lnyB7U/default.jpg",
            "width": 120,
            "height": 90
          },
          "medium": {
            "url": "https://i.ytimg.com/vi/UVoh1lnyB7U/mqdefault.jpg",
            "width": 320,
            "height": 180
          },
          "high": {
            "url": "https://i.ytimg.com/vi/UVoh1lnyB7U/hqdefault.jpg",
            "width": 480,
            "height": 360
          }
        },
        "channelTitle": "International Federation of Sport Climbing",
        "liveBroadcastContent": "none",
        "publishTime": "2022-09-25T01:46:31Z"
      }
    },
    {
      "kind": "youtube#searchResult",
      "etag": "uJQhEsXcxBOYCh7mkSWRbRX8hQQ",
      "id": {
        "kind": "youtube#video",
        "videoId": "I55Ix9t47Ks"
      },
      "snippet": {
        "publishedAt": "2022-09-14T07:58:26Z",
        "channelId": "UC2MGuhIaOP6YLpUx106kTQw",
        "title": "Lead finals highlights || Edinburgh 2022",
        "description": "The IFSC World Cup Series 2022 will return to Great Britain this week for Lead and Speed in Edinburgh, Scotland, from 9 to 11 ...",
        "thumbnails": {
          "default": {
            "url": "https://i.ytimg.com/vi/I55Ix9t47Ks/default.jpg",
            "width": 120,
            "height": 90
          },
          "medium": {
            "url": "https://i.ytimg.com/vi/I55Ix9t47Ks/mqdefault.jpg",
            "width": 320,
            "height": 180
          },
          "high": {
            "url": "https://i.ytimg.com/vi/I55Ix9t47Ks/hqdefault.jpg",
            "width": 480,
            "height": 360
          }
        },
        "channelTitle": "International Federation of Sport Climbing",
        "liveBroadcastContent": "none",
        "publishTime": "2022-09-14T07:58:26Z"
      }
    },
    {
      "kind": "youtube#searchResult",
      "etag": "hiV0SA3i2_Sq2_vuayAmAF5ffwU",
      "id": {
        "kind": "youtube#video",
        "videoId": "pPiXnlhGCs8"
      },
      "snippet": {
        "publishedAt": "2022-09-11T19:29:51Z",
        "channelId": "UC2MGuhIaOP6YLpUx106kTQw",
        "title": "Lead finals || Edinburgh 2022",
        "description": "The IFSC World Cup Series 2022 will return to Great Britain this week for Lead and Speed in Edinburgh, Scotland, from 9 to 11 ...",
        "thumbnails": {
          "default": {
            "url": "https://i.ytimg.com/vi/pPiXnlhGCs8/default.jpg",
            "width": 120,
            "height": 90
          },
          "medium": {
            "url": "https://i.ytimg.com/vi/pPiXnlhGCs8/mqdefault.jpg",
            "width": 320,
            "height": 180
          },
          "high": {
            "url": "https://i.ytimg.com/vi/pPiXnlhGCs8/hqdefault.jpg",
            "width": 480,
            "height": 360
          }
        },
        "channelTitle": "International Federation of Sport Climbing",
        "liveBroadcastContent": "none",
        "publishTime": "2022-09-11T19:29:51Z"
      }
    },
    {
      "kind": "youtube#searchResult",
      "etag": "yf26g5ZDkOdQ3qJPZ4Br28zw8JY",
      "id": {
        "kind": "youtube#video",
        "videoId": "D-Z-AaKMePE"
      },
      "snippet": {
        "publishedAt": "2022-09-11T13:00:13Z",
        "channelId": "UC2MGuhIaOP6YLpUx106kTQw",
        "title": "Lead semi-finals || Edinburgh 2022",
        "description": "The IFSC World Cup Series 2022 will return to Great Britain this week for Lead and Speed in Edinburgh, Scotland, from 9 to 11 ...",
        "thumbnails": {
          "default": {
            "url": "https://i.ytimg.com/vi/D-Z-AaKMePE/default.jpg",
            "width": 120,
            "height": 90
          },
          "medium": {
            "url": "https://i.ytimg.com/vi/D-Z-AaKMePE/mqdefault.jpg",
            "width": 320,
            "height": 180
          },
          "high": {
            "url": "https://i.ytimg.com/vi/D-Z-AaKMePE/hqdefault.jpg",
            "width": 480,
            "height": 360
          }
        },
        "channelTitle": "International Federation of Sport Climbing",
        "liveBroadcastContent": "none",
        "publishTime": "2022-09-11T13:00:13Z"
      }
    },
    {
      "kind": "youtube#searchResult",
      "etag": "SwM14V3z9wkdzLHTUZg-mCJlGmc",
      "id": {
        "kind": "youtube#video",
        "videoId": "0NjhIkR8kVM"
      },
      "snippet": {
        "publishedAt": "2022-09-11T00:06:32Z",
        "channelId": "UC2MGuhIaOP6YLpUx106kTQw",
        "title": "Lead qualifications highlights || Edinburgh 2022",
        "description": "The IFSC World Cup Series 2022 will return to Great Britain this week for Lead and Speed in Edinburgh, Scotland, from 9 to 11 ...",
        "thumbnails": {
          "default": {
            "url": "https://i.ytimg.com/vi/0NjhIkR8kVM/default.jpg",
            "width": 120,
            "height": 90
          },
          "medium": {
            "url": "https://i.ytimg.com/vi/0NjhIkR8kVM/mqdefault.jpg",
            "width": 320,
            "height": 180
          },
          "high": {
            "url": "https://i.ytimg.com/vi/0NjhIkR8kVM/hqdefault.jpg",
            "width": 480,
            "height": 360
          }
        },
        "channelTitle": "International Federation of Sport Climbing",
        "liveBroadcastContent": "none",
        "publishTime": "2022-09-11T00:06:32Z"
      }
    },
    {
      "kind": "youtube#searchResult",
      "etag": "cxJgOnP-DnzqOzSZuD-tIK4cS8c",
      "id": {
        "kind": "youtube#video",
        "videoId": "bghnLi1W_Cc"
      },
      "snippet": {
        "publishedAt": "2022-09-04T10:27:41Z",
        "channelId": "UC2MGuhIaOP6YLpUx106kTQw",
        "title": "Lead finals highlights || Koper 2022",
        "description": "More news: https://bit.ly/3ivwb9v Subscribe: https://bit.ly/3oveCdv.",
        "thumbnails": {
          "default": {
            "url": "https://i.ytimg.com/vi/bghnLi1W_Cc/default.jpg",
            "width": 120,
            "height": 90
          },
          "medium": {
            "url": "https://i.ytimg.com/vi/bghnLi1W_Cc/mqdefault.jpg",
            "width": 320,
            "height": 180
          },
          "high": {
            "url": "https://i.ytimg.com/vi/bghnLi1W_Cc/hqdefault.jpg",
            "width": 480,
            "height": 360
          }
        },
        "channelTitle": "International Federation of Sport Climbing",
        "liveBroadcastContent": "none",
        "publishTime": "2022-09-04T10:27:41Z"
      }
    },
    {
      "kind": "youtube#searchResult",
      "etag": "slqXBmXPGPMOuBmBTbuPlOqmMNA",
      "id": {
        "kind": "youtube#video",
        "videoId": "dGdqIBviuiA"
      },
      "snippet": {
        "publishedAt": "2022-09-03T20:16:28Z",
        "channelId": "UC2MGuhIaOP6YLpUx106kTQw",
        "title": "Lead finals || Koper 2022",
        "description": "More news: https://bit.ly/3ivwb9v Subscribe: https://bit.ly/3oveCdv.",
        "thumbnails": {
          "default": {
            "url": "https://i.ytimg.com/vi/dGdqIBviuiA/default.jpg",
            "width": 120,
            "height": 90
          },
          "medium": {
            "url": "https://i.ytimg.com/vi/dGdqIBviuiA/mqdefault.jpg",
            "width": 320,
            "height": 180
          },
          "high": {
            "url": "https://i.ytimg.com/vi/dGdqIBviuiA/hqdefault.jpg",
            "width": 480,
            "height": 360
          }
        },
        "channelTitle": "International Federation of Sport Climbing",
        "liveBroadcastContent": "none",
        "publishTime": "2022-09-03T20:16:28Z"
      }
    },
    {
      "kind": "youtube#searchResult",
      "etag": "slOSHT6Y3PoiVTBJfa8-7umzOvA",
      "id": {
        "kind": "youtube#video",
        "videoId": "IzA1geC9iFY"
      },
      "snippet": {
        "publishedAt": "2022-09-03T11:44:05Z",
        "channelId": "UC2MGuhIaOP6YLpUx106kTQw",
        "title": "Lead semi-finals highlights || Koper 2022",
        "description": "More news: https://bit.ly/3ivwb9v Subscribe: https://bit.ly/3oveCdv.",
        "thumbnails": {
          "default": {
            "url": "https://i.ytimg.com/vi/IzA1geC9iFY/default.jpg",
            "width": 120,
            "height": 90
          },
          "medium": {
            "url": "https://i.ytimg.com/vi/IzA1geC9iFY/mqdefault.jpg",
            "width": 320,
            "height": 180
          },
          "high": {
            "url": "https://i.ytimg.com/vi/IzA1geC9iFY/hqdefault.jpg",
            "width": 480,
            "height": 360
          }
        },
        "channelTitle": "International Federation of Sport Climbing",
        "liveBroadcastContent": "none",
        "publishTime": "2022-09-03T11:44:05Z"
      }
    },
    {
      "kind": "youtube#searchResult",
      "etag": "DtUOUP4sfsWE98l52VRnCzZ8JRA",
      "id": {
        "kind": "youtube#video",
        "videoId": "Djm5CQg3gBw"
      },
      "snippet": {
        "publishedAt": "2022-09-02T21:03:36Z",
        "channelId": "UC2MGuhIaOP6YLpUx106kTQw",
        "title": "Lead semi-finals || Koper 2022",
        "description": "More news: https://bit.ly/3ivwb9v Subscribe: https://bit.ly/3oveCdv.",
        "thumbnails": {
          "default": {
            "url": "https://i.ytimg.com/vi/Djm5CQg3gBw/default.jpg",
            "width": 120,
            "height": 90
          },
          "medium": {
            "url": "https://i.ytimg.com/vi/Djm5CQg3gBw/mqdefault.jpg",
            "width": 320,
            "height": 180
          },
          "high": {
            "url": "https://i.ytimg.com/vi/Djm5CQg3gBw/hqdefault.jpg",
            "width": 480,
            "height": 360
          }
        },
        "channelTitle": "International Federation of Sport Climbing",
        "liveBroadcastContent": "none",
        "publishTime": "2022-09-02T21:03:36Z"
      }
    },
    {
      "kind": "youtube#searchResult",
      "etag": "N78aLrtTlp_DbNhIoz2pCiY5qXI",
      "id": {
        "kind": "youtube#video",
        "videoId": "oNmuP_9IbE0"
      },
      "snippet": {
        "publishedAt": "2022-08-31T21:47:56Z",
        "channelId": "UC2MGuhIaOP6YLpUx106kTQw",
        "title": "U16, men&#39;s U18 Lead finals || Youth Worlds Dallas 2022",
        "description": "More news: https://bit.ly/3ivwb9v Subscribe: https://bit.ly/3oveCdv.",
        "thumbnails": {
          "default": {
            "url": "https://i.ytimg.com/vi/oNmuP_9IbE0/default.jpg",
            "width": 120,
            "height": 90
          },
          "medium": {
            "url": "https://i.ytimg.com/vi/oNmuP_9IbE0/mqdefault.jpg",
            "width": 320,
            "height": 180
          },
          "high": {
            "url": "https://i.ytimg.com/vi/oNmuP_9IbE0/hqdefault.jpg",
            "width": 480,
            "height": 360
          }
        },
        "channelTitle": "International Federation of Sport Climbing",
        "liveBroadcastContent": "none",
        "publishTime": "2022-08-31T21:47:56Z"
      }
    },
    {
      "kind": "youtube#searchResult",
      "etag": "R7IQLw9UrxbWpPqzzm_fksv3jSU",
      "id": {
        "kind": "youtube#video",
        "videoId": "Slx-3IzQigw"
      },
      "snippet": {
        "publishedAt": "2022-08-31T16:33:07Z",
        "channelId": "UC2MGuhIaOP6YLpUx106kTQw",
        "title": "U16, men&#39;s U18 Lead semi-finals || Youth Worlds Dallas 2022",
        "description": "More news: https://bit.ly/3ivwb9v Subscribe: https://bit.ly/3oveCdv.",
        "thumbnails": {
          "default": {
            "url": "https://i.ytimg.com/vi/Slx-3IzQigw/default.jpg",
            "width": 120,
            "height": 90
          },
          "medium": {
            "url": "https://i.ytimg.com/vi/Slx-3IzQigw/mqdefault.jpg",
            "width": 320,
            "height": 180
          },
          "high": {
            "url": "https://i.ytimg.com/vi/Slx-3IzQigw/hqdefault.jpg",
            "width": 480,
            "height": 360
          }
        },
        "channelTitle": "International Federation of Sport Climbing",
        "liveBroadcastContent": "none",
        "publishTime": "2022-08-31T16:33:07Z"
      }
    },
    {
      "kind": "youtube#searchResult",
      "etag": "6SwSRikZY4mrVrcHON03y9gW8bI",
      "id": {
        "kind": "youtube#video",
        "videoId": "04y42IO0-BA"
      },
      "snippet": {
        "publishedAt": "2022-08-30T22:16:50Z",
        "channelId": "UC2MGuhIaOP6YLpUx106kTQw",
        "title": "Women&#39;s U18, U20 Lead finals || Youth Worlds Dallas 2022",
        "description": "More news: https://bit.ly/3ivwb9v Subscribe: https://bit.ly/3oveCdv.",
        "thumbnails": {
          "default": {
            "url": "https://i.ytimg.com/vi/04y42IO0-BA/default.jpg",
            "width": 120,
            "height": 90
          },
          "medium": {
            "url": "https://i.ytimg.com/vi/04y42IO0-BA/mqdefault.jpg",
            "width": 320,
            "height": 180
          },
          "high": {
            "url": "https://i.ytimg.com/vi/04y42IO0-BA/hqdefault.jpg",
            "width": 480,
            "height": 360
          }
        },
        "channelTitle": "International Federation of Sport Climbing",
        "liveBroadcastContent": "none",
        "publishTime": "2022-08-30T22:16:50Z"
      }
    },
    {
      "kind": "youtube#searchResult",
      "etag": "w0ozrNO_FJsKYd-QHv_xbukCC5A",
      "id": {
        "kind": "youtube#video",
        "videoId": "f1sfE58L4ek"
      },
      "snippet": {
        "publishedAt": "2022-08-30T16:47:08Z",
        "channelId": "UC2MGuhIaOP6YLpUx106kTQw",
        "title": "Women&#39;s U18, U20 Lead semi-finals || Youth Worlds Dallas 2022",
        "description": "More news: https://bit.ly/3ivwb9v Subscribe: https://bit.ly/3oveCdv.",
        "thumbnails": {
          "default": {
            "url": "https://i.ytimg.com/vi/f1sfE58L4ek/default.jpg",
            "width": 120,
            "height": 90
          },
          "medium": {
            "url": "https://i.ytimg.com/vi/f1sfE58L4ek/mqdefault.jpg",
            "width": 320,
            "height": 180
          },
          "high": {
            "url": "https://i.ytimg.com/vi/f1sfE58L4ek/hqdefault.jpg",
            "width": 480,
            "height": 360
          }
        },
        "channelTitle": "International Federation of Sport Climbing",
        "liveBroadcastContent": "none",
        "publishTime": "2022-08-30T16:47:08Z"
      }
    },
    {
      "kind": "youtube#searchResult",
      "etag": "w9NR9ol3nCjxjZURjVwjHZgijCs",
      "id": {
        "kind": "youtube#video",
        "videoId": "1BYz5TvJUDs"
      },
      "snippet": {
        "publishedAt": "2022-08-29T14:18:38Z",
        "channelId": "UC2MGuhIaOP6YLpUx106kTQw",
        "title": "How hard are the Youth Worlds qualification routes? || Youth Worlds Dallas 2022",
        "description": "Climbing routes always seem to look easy on T.V…but how hard are they really? We get a local wad to climb the route, and break ...",
        "thumbnails": {
          "default": {
            "url": "https://i.ytimg.com/vi/1BYz5TvJUDs/default.jpg",
            "width": 120,
            "height": 90
          },
          "medium": {
            "url": "https://i.ytimg.com/vi/1BYz5TvJUDs/mqdefault.jpg",
            "width": 320,
            "height": 180
          },
          "high": {
            "url": "https://i.ytimg.com/vi/1BYz5TvJUDs/hqdefault.jpg",
            "width": 480,
            "height": 360
          }
        },
        "channelTitle": "International Federation of Sport Climbing",
        "liveBroadcastContent": "none",
        "publishTime": "2022-08-29T14:18:38Z"
      }
    },
    {
      "kind": "youtube#searchResult",
      "etag": "W3w_B47NUUPyS0qtfgrdJgBnGtM",
      "id": {
        "kind": "youtube#video",
        "videoId": "DDE2Sc2kmPI"
      },
      "snippet": {
        "publishedAt": "2022-08-27T18:46:34Z",
        "channelId": "UC2MGuhIaOP6YLpUx106kTQw",
        "title": "U16 Speed finals || Youth Worlds Dallas 2022",
        "description": "More news: https://bit.ly/3ivwb9v Subscribe: https://bit.ly/3oveCdv.",
        "thumbnails": {
          "default": {
            "url": "https://i.ytimg.com/vi/DDE2Sc2kmPI/default.jpg",
            "width": 120,
            "height": 90
          },
          "medium": {
            "url": "https://i.ytimg.com/vi/DDE2Sc2kmPI/mqdefault.jpg",
            "width": 320,
            "height": 180
          },
          "high": {
            "url": "https://i.ytimg.com/vi/DDE2Sc2kmPI/hqdefault.jpg",
            "width": 480,
            "height": 360
          }
        },
        "channelTitle": "International Federation of Sport Climbing",
        "liveBroadcastContent": "none",
        "publishTime": "2022-08-27T18:46:34Z"
      }
    },
    {
      "kind": "youtube#searchResult",
      "etag": "vueoMPoYOd6lf_71dToWApoO5FQ",
      "id": {
        "kind": "youtube#video",
        "videoId": "36eVdV3fH9M"
      },
      "snippet": {
        "publishedAt": "2022-08-26T14:35:54Z",
        "channelId": "UC2MGuhIaOP6YLpUx106kTQw",
        "title": "Full highlights and action from the U16 finals || Youth Worlds Dallas 2022",
        "description": "Today we are just focusing on the Youth B finals, some of the youngest climbers competing at the Youth World Championships.",
        "thumbnails": {
          "default": {
            "url": "https://i.ytimg.com/vi/36eVdV3fH9M/default.jpg",
            "width": 120,
            "height": 90
          },
          "medium": {
            "url": "https://i.ytimg.com/vi/36eVdV3fH9M/mqdefault.jpg",
            "width": 320,
            "height": 180
          },
          "high": {
            "url": "https://i.ytimg.com/vi/36eVdV3fH9M/hqdefault.jpg",
            "width": 480,
            "height": 360
          }
        },
        "channelTitle": "International Federation of Sport Climbing",
        "liveBroadcastContent": "none",
        "publishTime": "2022-08-26T14:35:54Z"
      }
    },
    {
      "kind": "youtube#searchResult",
      "etag": "UtWzcDSOKYfQft1Kysf6da0JcDc",
      "id": {
        "kind": "youtube#video",
        "videoId": "iRMvcBjYOxw"
      },
      "snippet": {
        "publishedAt": "2022-08-24T13:58:29Z",
        "channelId": "UC2MGuhIaOP6YLpUx106kTQw",
        "title": "The toughest job in Climbing || Youth Worlds Dallas 2022",
        "description": "It's day two at the Youth World Championships and we followed team GB's coaches as they prepared their athletes to compete.",
        "thumbnails": {
          "default": {
            "url": "https://i.ytimg.com/vi/iRMvcBjYOxw/default.jpg",
            "width": 120,
            "height": 90
          },
          "medium": {
            "url": "https://i.ytimg.com/vi/iRMvcBjYOxw/mqdefault.jpg",
            "width": 320,
            "height": 180
          },
          "high": {
            "url": "https://i.ytimg.com/vi/iRMvcBjYOxw/hqdefault.jpg",
            "width": 480,
            "height": 360
          }
        },
        "channelTitle": "International Federation of Sport Climbing",
        "liveBroadcastContent": "none",
        "publishTime": "2022-08-24T13:58:29Z"
      }
    }
  ]
}
