{
  "kind": "youtube#searchListResponse",
  "etag": "MP0PGTIf_gIe9XLMoLl4tLsVMbg",
  "nextPageToken": "CGQQAA",
  "prevPageToken": "CDIQAQ",
  "regionCode": "US",
  "pageInfo": {
    "totalResults": 1316,
    "resultsPerPage": 50
  },
  "items": [
    {
      "kind": "youtube#searchResult",
      "etag": "9jnlWN4Esl5KFjgm2qxmTzXP82U",
      "id": {
        "kind": "youtube#video",
        "videoId": "kbr74eVN5hc"
      },
      "snippet": {
        "publishedAt": "2022-08-23T14:54:07Z",
        "channelId": "UC2MGuhIaOP6YLpUx106kTQw",
        "title": "Boulder qualifications in Dallas || Youth Worlds Dallas 2022",
        "description": "Over 450 athletes have gathered in Dallas, Texas, for the Youth World Championships. We are bringing you a daily show, with our ...",
        "thumbnails": {
          "default": {
            "url": "https://i.ytimg.com/vi/kbr74eVN5hc/default.jpg",
            "width": 120,
            "height": 90
          },
          "medium": {
            "url": "https://i.ytimg.com/vi/kbr74eVN5hc/mqdefault.jpg",
            "width": 320,
            "height": 180
          },
          "high": {
            "url": "https://i.ytimg.com/vi/kbr74eVN5hc/hqdefault.jpg",
            "width": 480,
            "height": 360
          }
        },
        "channelTitle": "International Federation of Sport Climbing",
        "liveBroadcastContent": "none",
        "publishTime": "2022-08-23T14:54:07Z"
      }
    },
    {
      "kind": "youtube#searchResult",
      "etag": "6rgMcct9ZhCDxWnlNdpY6ueQVV8",
      "id": {
        "kind": "youtube#video",
        "videoId": "dyban7j2XtQ"
      },
      "snippet": {
        "publishedAt": "2022-07-24T14:27:30Z",
        "channelId": "UC2MGuhIaOP6YLpUx106kTQw",
        "title": "Lead finals highlights || Innsbruck 2022",
        "description": "The sixth stage of the International Federation of Sport Climbing (IFSC) World Cup Series 2022 will see the Boulder and Lead ...",
        "thumbnails": {
          "default": {
            "url": "https://i.ytimg.com/vi/dyban7j2XtQ/default.jpg",
            "width": 120,
            "height": 90
          },
          "medium": {
            "url": "https://i.ytimg.com/vi/dyban7j2XtQ/mqdefault.jpg",
            "width": 320,
            "height": 180
          },
          "high": {
            "url": "https://i.ytimg.com/vi/dyban7j2XtQ/hqdefault.jpg",
            "width": 480,
            "height": 360
          }
        },
        "channelTitle": "International Federation of Sport Climbing",
        "liveBroadcastContent": "none",
        "publishTime": "2022-07-24T14:27:30Z"
      }
    },
    {
      "kind": "youtube#searchResult",
      "etag": "nBeV_BgtYZ3Z2YMfpSAi1LQo0cI",
      "id": {
        "kind": "youtube#video",
        "videoId": "1H_MtCNlUz0"
      },
      "snippet": {
        "publishedAt": "2022-07-24T13:32:55Z",
        "channelId": "UC2MGuhIaOP6YLpUx106kTQw",
        "title": "Lead finals highlights || Briançon 2022",
        "description": "The French city of Briançon is set to welcome the fourth Lead competition of the International Federation of Sport Climbing (IFSC) ...",
        "thumbnails": {
          "default": {
            "url": "https://i.ytimg.com/vi/1H_MtCNlUz0/default.jpg",
            "width": 120,
            "height": 90
          },
          "medium": {
            "url": "https://i.ytimg.com/vi/1H_MtCNlUz0/mqdefault.jpg",
            "width": 320,
            "height": 180
          },
          "high": {
            "url": "https://i.ytimg.com/vi/1H_MtCNlUz0/hqdefault.jpg",
            "width": 480,
            "height": 360
          }
        },
        "channelTitle": "International Federation of Sport Climbing",
        "liveBroadcastContent": "none",
        "publishTime": "2022-07-24T13:32:55Z"
      }
    },
    {
      "kind": "youtube#searchResult",
      "etag": "vyBcjwbFkajo1qBoPiHW5X7DRLY",
      "id": {
        "kind": "youtube#video",
        "videoId": "qTRM_T9tL9I"
      },
      "snippet": {
        "publishedAt": "2022-07-23T20:38:13Z",
        "channelId": "UC2MGuhIaOP6YLpUx106kTQw",
        "title": "Lead finals || Briançon 2022",
        "description": "The French city of Briançon is set to welcome the fourth Lead competition of the International Federation of Sport Climbing (IFSC) ...",
        "thumbnails": {
          "default": {
            "url": "https://i.ytimg.com/vi/qTRM_T9tL9I/default.jpg",
            "width": 120,
            "height": 90
          },
          "medium": {
            "url": "https://i.ytimg.com/vi/qTRM_T9tL9I/mqdefault.jpg",
            "width": 320,
            "height": 180
          },
          "high": {
            "url": "https://i.ytimg.com/vi/qTRM_T9tL9I/hqdefault.jpg",
            "width": 480,
            "height": 360
          }
        },
        "channelTitle": "International Federation of Sport Climbing",
        "liveBroadcastContent": "none",
        "publishTime": "2022-07-23T20:38:13Z"
      }
    },
    {
      "kind": "youtube#searchResult",
      "etag": "LOW7RUZOCEI0pjdrOSxMn9xwEPI",
      "id": {
        "kind": "youtube#video",
        "videoId": "o4KnxxnS7LE"
      },
      "snippet": {
        "publishedAt": "2022-07-23T07:35:01Z",
        "channelId": "UC2MGuhIaOP6YLpUx106kTQw",
        "title": "Lead semi-finals highlights || Briançon 2022",
        "description": "The French city of Briançon is set to welcome the fourth Lead competition of the International Federation of Sport Climbing (IFSC) ...",
        "thumbnails": {
          "default": {
            "url": "https://i.ytimg.com/vi/o4KnxxnS7LE/default.jpg",
            "width": 120,
            "height": 90
          },
          "medium": {
            "url": "https://i.ytimg.com/vi/o4KnxxnS7LE/mqdefault.jpg",
            "width": 320,
            "height": 180
          },
          "high": {
            "url": "https://i.ytimg.com/vi/o4KnxxnS7LE/hqdefault.jpg",
            "width": 480,
            "height": 360
          }
        },
        "channelTitle": "International Federation of Sport Climbing",
        "liveBroadcastContent": "none",
        "publishTime": "2022-07-23T07:35:01Z"
      }
    },
    {
      "kind": "youtube#searchResult",
      "etag": "X-s529xpMXe9TD3YvB9uKDBaZAQ",
      "id": {
        "kind": "youtube#video",
        "videoId": "VnD1T_gq1zU"
      },
      "snippet": {
        "publishedAt": "2022-07-22T22:19:15Z",
        "channelId": "UC2MGuhIaOP6YLpUx106kTQw",
        "title": "Lead semi-finals || Briançon 2022",
        "description": "The French city of Briançon is set to welcome the fourth Lead competition of the International Federation of Sport Climbing (IFSC) ...",
        "thumbnails": {
          "default": {
            "url": "https://i.ytimg.com/vi/VnD1T_gq1zU/default.jpg",
            "width": 120,
            "height": 90
          },
          "medium": {
            "url": "https://i.ytimg.com/vi/VnD1T_gq1zU/mqdefault.jpg",
            "width": 320,
            "height": 180
          },
          "high": {
            "url": "https://i.ytimg.com/vi/VnD1T_gq1zU/hqdefault.jpg",
            "width": 480,
            "height": 360
          }
        },
        "channelTitle": "International Federation of Sport Climbing",
        "liveBroadcastContent": "none",
        "publishTime": "2022-07-22T22:19:15Z"
      }
    },
    {
      "kind": "youtube#searchResult",
      "etag": "SxtT52XLdE4jkGVd6J-FSfBecc4",
      "id": {
        "kind": "youtube#video",
        "videoId": "joqGl_g3o94"
      },
      "snippet": {
        "publishedAt": "2022-07-12T06:24:02Z",
        "channelId": "UC2MGuhIaOP6YLpUx106kTQw",
        "title": "Lead finals highlights || Chamonix 2022",
        "description": "This weekend, the International Federation of Sport Climbing (IFSC) World Cup Series 2022 continues in Chamonix, France, ...",
        "thumbnails": {
          "default": {
            "url": "https://i.ytimg.com/vi/joqGl_g3o94/default.jpg",
            "width": 120,
            "height": 90
          },
          "medium": {
            "url": "https://i.ytimg.com/vi/joqGl_g3o94/mqdefault.jpg",
            "width": 320,
            "height": 180
          },
          "high": {
            "url": "https://i.ytimg.com/vi/joqGl_g3o94/hqdefault.jpg",
            "width": 480,
            "height": 360
          }
        },
        "channelTitle": "International Federation of Sport Climbing",
        "liveBroadcastContent": "none",
        "publishTime": "2022-07-12T06:24:02Z"
      }
    },
    {
      "kind": "youtube#searchResult",
      "etag": "opLEIdtHMDMvqnO5WeXKHs3ojRM",
      "id": {
        "kind": "youtube#video",
        "videoId": "_wIP_73GTYQ"
      },
      "snippet": {
        "publishedAt": "2022-07-10T21:34:41Z",
        "channelId": "UC2MGuhIaOP6YLpUx106kTQw",
        "title": "Lead finals || Chamonix 2022",
        "description": "More news: https://bit.ly/3ivwb9v Subscribe: https://bit.ly/3oveCdv.",
        "thumbnails": {
          "default": {
            "url": "https://i.ytimg.com/vi/_wIP_73GTYQ/default.jpg",
            "width": 120,
            "height": 90
          },
          "medium": {
            "url": "https://i.ytimg.com/vi/_wIP_73GTYQ/mqdefault.jpg",
            "width": 320,
            "height": 180
          },
          "high": {
            "url": "https://i.ytimg.com/vi/_wIP_73GTYQ/hqdefault.jpg",
            "width": 480,
            "height": 360
          }
        },
        "channelTitle": "International Federation of Sport Climbing",
        "liveBroadcastContent": "none",
        "publishTime": "2022-07-10T21:34:41Z"
      }
    },
    {
      "kind": "youtube#searchResult",
      "etag": "HUkR2GAa6QobV4A93D2IO_ReJ7k",
      "id": {
        "kind": "youtube#video",
        "videoId": "atk-jed2EOA"
      },
      "snippet": {
        "publishedAt": "2022-07-10T07:48:38Z",
        "channelId": "UC2MGuhIaOP6YLpUx106kTQw",
        "title": "Speed finals highlights || Chamonix 2022",
        "description": "This weekend, the International Federation of Sport Climbing (IFSC) World Cup Series 2022 continues in Chamonix, France, ...",
        "thumbnails": {
          "default": {
            "url": "https://i.ytimg.com/vi/atk-jed2EOA/default.jpg",
            "width": 120,
            "height": 90
          },
          "medium": {
            "url": "https://i.ytimg.com/vi/atk-jed2EOA/mqdefault.jpg",
            "width": 320,
            "height": 180
          },
          "high": {
            "url": "https://i.ytimg.com/vi/atk-jed2EOA/hqdefault.jpg",
            "width": 480,
            "height": 360
          }
        },
        "channelTitle": "International Federation of Sport Climbing",
        "liveBroadcastContent": "none",
        "publishTime": "2022-07-10T07:48:38Z"
      }
    },
    {
      "kind": "youtube#searchResult",
      "etag": "wGOgorl3bLNRlGH5zXJoMcsQfmQ",
      "id": {
        "kind": "youtube#video",
        "videoId": "AQBsXKPk2bY"
      },
      "snippet": {
        "publishedAt": "2022-07-09T22:03:25Z",
        "channelId": "UC2MGuhIaOP6YLpUx106kTQw",
        "title": "Lead qualifications highlights || Chamonix 2022",
        "description": "This weekend, the International Federation of Sport Climbing (IFSC) World Cup Series 2022 continues in Chamonix, France, ...",
        "thumbnails": {
          "default": {
            "url": "https://i.ytimg.com/vi/AQBsXKPk2bY/default.jpg",
            "width": 120,
            "height": 90
          },
          "medium": {
            "url": "https://i.ytimg.com/vi/AQBsXKPk2bY/mqdefault.jpg",
            "width": 320,
            "height": 180
          },
          "high": {
            "url": "https://i.ytimg.com/vi/AQBsXKPk2bY/hqdefault.jpg",
            "width": 480,
            "height": 360
          }
        },
        "channelTitle": "International Federation of Sport Climbing",
        "liveBroadcastContent": "none",
        "publishTime": "2022-07-09T22:03:25Z"
      }
    },
    {
      "kind": "youtube#searchResult",
      "etag": "ZiORpZhRNdnYzKRLKnN2xHx3WVY",
      "id": {
        "kind": "youtube#video",
        "videoId": "Pm1BoMZpbgE"
      },
      "snippet": {
        "publishedAt": "2022-07-09T20:39:41Z",
        "channelId": "UC2MGuhIaOP6YLpUx106kTQw",
        "title": "Speed finals || Chamonix 2022",
        "description": "More news: https://bit.ly/3ivwb9v Subscribe: https://bit.ly/3oveCdv.",
        "thumbnails": {
          "default": {
            "url": "https://i.ytimg.com/vi/Pm1BoMZpbgE/default.jpg",
            "width": 120,
            "height": 90
          },
          "medium": {
            "url": "https://i.ytimg.com/vi/Pm1BoMZpbgE/mqdefault.jpg",
            "width": 320,
            "height": 180
          },
          "high": {
            "url": "https://i.ytimg.com/vi/Pm1BoMZpbgE/hqdefault.jpg",
            "width": 480,
            "height": 360
          }
        },
        "channelTitle": "International Federation of Sport Climbing",
        "liveBroadcastContent": "none",
        "publishTime": "2022-07-09T20:39:41Z"
      }
    },
    {
      "kind": "youtube#searchResult",
      "etag": "gehF5sPYjhuMZ2i_uMS_esUgIjc",
      "id": {
        "kind": "youtube#video",
        "videoId": "nbz7V8GcAHg"
      },
      "snippet": {
        "publishedAt": "2022-07-08T22:34:18Z",
        "channelId": "UC2MGuhIaOP6YLpUx106kTQw",
        "title": "Kiromal Katibin&#39;s 🇮🇩 5-second record in slo-mo! 🤯",
        "description": "The 21-year-old from Batang, Central Java, Indonesia, shocked the crowd that gathered at Place du Mont Blanc on a sunny ...",
        "thumbnails": {
          "default": {
            "url": "https://i.ytimg.com/vi/nbz7V8GcAHg/default.jpg",
            "width": 120,
            "height": 90
          },
          "medium": {
            "url": "https://i.ytimg.com/vi/nbz7V8GcAHg/mqdefault.jpg",
            "width": 320,
            "height": 180
          },
          "high": {
            "url": "https://i.ytimg.com/vi/nbz7V8GcAHg/hqdefault.jpg",
            "width": 480,
            "height": 360
          }
        },
        "channelTitle": "International Federation of Sport Climbing",
        "liveBroadcastContent": "none",
        "publishTime": "2022-07-08T22:34:18Z"
      }
    },
    {
      "kind": "youtube#searchResult",
      "etag": "hm8_f6F7SvJNQVLqRRUxr00_S9E",
      "id": {
        "kind": "youtube#video",
        "videoId": "vHM4fO70fzM"
      },
      "snippet": {
        "publishedAt": "2022-07-02T23:38:34Z",
        "channelId": "UC2MGuhIaOP6YLpUx106kTQw",
        "title": "Lead finals highlights || Villars 2022",
        "description": "The International Federation of Sport Climbing (IFSC) World Cup Series 2022 is set to continue in the Swiss village of Villars this ...",
        "thumbnails": {
          "default": {
            "url": "https://i.ytimg.com/vi/vHM4fO70fzM/default.jpg",
            "width": 120,
            "height": 90
          },
          "medium": {
            "url": "https://i.ytimg.com/vi/vHM4fO70fzM/mqdefault.jpg",
            "width": 320,
            "height": 180
          },
          "high": {
            "url": "https://i.ytimg.com/vi/vHM4fO70fzM/hqdefault.jpg",
            "width": 480,
            "height": 360
          }
        },
        "channelTitle": "International Federation of Sport Climbing",
        "liveBroadcastContent": "none",
        "publishTime": "2022-07-02T23:38:34Z"
      }
    },
    {
      "kind": "youtube#searchResult",
      "etag": "LUQqjVOOvoCBzPk_M88ZjwT4GjM",
      "id": {
        "kind": "youtube#video",
        "videoId": "FGn389IsNxQ"
      },
      "snippet": {
        "publishedAt": "2022-07-02T20:35:54Z",
        "channelId": "UC2MGuhIaOP6YLpUx106kTQw",
        "title": "Lead finals || Villars 2022",
        "description": "The International Federation of Sport Climbing (IFSC) World Cup Series 2022 is set to continue in the Swiss village of Villars this ...",
        "thumbnails": {
          "default": {
            "url": "https://i.ytimg.com/vi/FGn389IsNxQ/default.jpg",
            "width": 120,
            "height": 90
          },
          "medium": {
            "url": "https://i.ytimg.com/vi/FGn389IsNxQ/mqdefault.jpg",
            "width": 320,
            "height": 180
          },
          "high": {
            "url": "https://i.ytimg.com/vi/FGn389IsNxQ/hqdefault.jpg",
            "width": 480,
            "height": 360
          }
        },
        "channelTitle": "International Federation of Sport Climbing",
        "liveBroadcastContent": "none",
        "publishTime": "2022-07-02T20:35:54Z"
      }
    },
    {
      "kind": "youtube#searchResult",
      "etag": "xNvQyMW6793AIMA87IlkovA4cmc",
      "id": {
        "kind": "youtube#video",
        "videoId": "UStvBrRcnnQ"
      },
      "snippet": {
        "publishedAt": "2022-07-02T16:42:31Z",
        "channelId": "UC2MGuhIaOP6YLpUx106kTQw",
        "title": "Lead semi-finals || Villars 2022",
        "description": "The International Federation of Sport Climbing (IFSC) World Cup Series 2022 is set to continue in the Swiss village of Villars this ...",
        "thumbnails": {
          "default": {
            "url": "https://i.ytimg.com/vi/UStvBrRcnnQ/default.jpg",
            "width": 120,
            "height": 90
          },
          "medium": {
            "url": "https://i.ytimg.com/vi/UStvBrRcnnQ/mqdefault.jpg",
            "width": 320,
            "height": 180
          },
          "high": {
            "url": "https://i.ytimg.com/vi/UStvBrRcnnQ/hqdefault.jpg",
            "width": 480,
            "height": 360
          }
        },
        "channelTitle": "International Federation of Sport Climbing",
        "liveBroadcastContent": "none",
        "publishTime": "2022-07-02T16:42:31Z"
      }
    },
    {
      "kind": "youtube#searchResult",
      "etag": "ieNzqNQA6LSOJxOsR_EVJ4OAwa0",
      "id": {
        "kind": "youtube#video",
        "videoId": "gOzoNg_2Bss"
      },
      "snippet": {
        "publishedAt": "2022-07-01T23:55:33Z",
        "channelId": "UC2MGuhIaOP6YLpUx106kTQw",
        "title": "Speed finals highlights || Villars 2022",
        "description": "The International Federation of Sport Climbing (IFSC) World Cup Series 2022 is set to continue in the Swiss village of Villars this ...",
        "thumbnails": {
          "default": {
            "url": "https://i.ytimg.com/vi/gOzoNg_2Bss/default.jpg",
            "width": 120,
            "height": 90
          },
          "medium": {
            "url": "https://i.ytimg.com/vi/gOzoNg_2Bss/mqdefault.jpg",
            "width": 320,
            "height": 180
          },
          "high": {
            "url": "https://i.ytimg.com/vi/gOzoNg_2Bss/hqdefault.jpg",
            "width": 480,
            "height": 360
          }
        },
        "channelTitle": "International Federation of Sport Climbing",
        "liveBroadcastContent": "none",
        "publishTime": "2022-07-01T23:55:33Z"
      }
    },
    {
      "kind": "youtube#searchResult",
      "etag": "YL9xa7S_3AjAd9LGV7S7tUe_eZM",
      "id": {
        "kind": "youtube#video",
        "videoId": "QgYmP41LfMk"
      },
      "snippet": {
        "publishedAt": "2022-07-01T21:39:36Z",
        "channelId": "UC2MGuhIaOP6YLpUx106kTQw",
        "title": "Lead qualifications highlights || Villars 2022",
        "description": "The International Federation of Sport Climbing (IFSC) World Cup Series 2022 is set to continue in the Swiss village of Villars this ...",
        "thumbnails": {
          "default": {
            "url": "https://i.ytimg.com/vi/QgYmP41LfMk/default.jpg",
            "width": 120,
            "height": 90
          },
          "medium": {
            "url": "https://i.ytimg.com/vi/QgYmP41LfMk/mqdefault.jpg",
            "width": 320,
            "height": 180
          },
          "high": {
            "url": "https://i.ytimg.com/vi/QgYmP41LfMk/hqdefault.jpg",
            "width": 480,
            "height": 360
          }
        },
        "channelTitle": "International Federation of Sport Climbing",
        "liveBroadcastContent": "none",
        "publishTime": "2022-07-01T21:39:36Z"
      }
    },
    {
      "kind": "youtube#searchResult",
      "etag": "GHn9_ChzKjC973iOL33MRIsSBS0",
      "id": {
        "kind": "youtube#video",
        "videoId": "I9V_E_g3uBA"
      },
      "snippet": {
        "publishedAt": "2022-07-01T21:02:12Z",
        "channelId": "UC2MGuhIaOP6YLpUx106kTQw",
        "title": "Speed finals || Villars 2022",
        "description": "The International Federation of Sport Climbing (IFSC) World Cup Series 2022 is set to continue in the Swiss village of Villars this ...",
        "thumbnails": {
          "default": {
            "url": "https://i.ytimg.com/vi/I9V_E_g3uBA/default.jpg",
            "width": 120,
            "height": 90
          },
          "medium": {
            "url": "https://i.ytimg.com/vi/I9V_E_g3uBA/mqdefault.jpg",
            "width": 320,
            "height": 180
          },
          "high": {
            "url": "https://i.ytimg.com/vi/I9V_E_g3uBA/hqdefault.jpg",
            "width": 480,
            "height": 360
          }
        },
        "channelTitle": "International Federation of Sport Climbing",
        "liveBroadcastContent": "none",
        "publishTime": "2022-07-01T21:02:12Z"
      }
    },
    {
      "kind": "youtube#searchResult",
      "etag": "IIBvupPtcDBz-NVZCVPcuc-HuNc",
      "id": {
        "kind": "youtube#video",
        "videoId": "z4a3gQC5J_c"
      },
      "snippet": {
        "publishedAt": "2022-06-30T17:09:05Z",
        "channelId": "UC2MGuhIaOP6YLpUx106kTQw",
        "title": "Forget the 5.09… HOW ABOUT FIVE-POINT-ZERO-FOUR!! KIROMAL KATIBIN 🇮🇩 IS FROM ANOTHER PLANET!!",
        "description": "",
        "thumbnails": {
          "default": {
            "url": "https://i.ytimg.com/vi/z4a3gQC5J_c/default.jpg",
            "width": 120,
            "height": 90
          },
          "medium": {
            "url": "https://i.ytimg.com/vi/z4a3gQC5J_c/mqdefault.jpg",
            "width": 320,
            "height": 180
          },
          "high": {
            "url": "https://i.ytimg.com/vi/z4a3gQC5J_c/hqdefault.jpg",
            "width": 480,
            "height": 360
          }
        },
        "channelTitle": "International Federation of Sport Climbing",
        "liveBroadcastContent": "none",
        "publishTime": "2022-06-30T17:09:05Z"
      }
    },
    {
      "kind": "youtube#searchResult",
      "etag": "ecm-vxGVUSG0Hb64chdj1PwgUbg",
      "id": {
        "kind": "youtube#video",
        "videoId": "Ob5feZFWuFI"
      },
      "snippet": {
        "publishedAt": "2022-06-30T14:06:20Z",
        "channelId": "UC2MGuhIaOP6YLpUx106kTQw",
        "title": "Kiromal Katibin 🇮🇩 tears down another barrier and set a new men’s Speed world record with 5.09!",
        "description": "",
        "thumbnails": {
          "default": {
            "url": "https://i.ytimg.com/vi/Ob5feZFWuFI/default.jpg",
            "width": 120,
            "height": 90
          },
          "medium": {
            "url": "https://i.ytimg.com/vi/Ob5feZFWuFI/mqdefault.jpg",
            "width": 320,
            "height": 180
          },
          "high": {
            "url": "https://i.ytimg.com/vi/Ob5feZFWuFI/hqdefault.jpg",
            "width": 480,
            "height": 360
          }
        },
        "channelTitle": "International Federation of Sport Climbing",
        "liveBroadcastContent": "none",
        "publishTime": "2022-06-30T14:06:20Z"
      }
    },
    {
      "kind": "youtube#searchResult",
      "etag": "KUsMDe3aXNu857tKSdhNlb83eZU",
      "id": {
        "kind": "youtube#video",
        "videoId": "SfhGW6Bwyks"
      },
      "snippet": {
        "publishedAt": "2022-06-26T19:51:54Z",
        "channelId": "UC2MGuhIaOP6YLpUx106kTQw",
        "title": "Lead finals || Innsbruck 2022",
        "description": "The Boulder and Lead seasons will cross-paths at the Kletterzentrum Innsbruck, where the sixth stage of the IFSC World Cup ...",
        "thumbnails": {
          "default": {
            "url": "https://i.ytimg.com/vi/SfhGW6Bwyks/default.jpg",
            "width": 120,
            "height": 90
          },
          "medium": {
            "url": "https://i.ytimg.com/vi/SfhGW6Bwyks/mqdefault.jpg",
            "width": 320,
            "height": 180
          },
          "high": {
            "url": "https://i.ytimg.com/vi/SfhGW6Bwyks/hqdefault.jpg",
            "width": 480,
            "height": 360
          }
        },
        "channelTitle": "International Federation of Sport Climbing",
        "liveBroadcastContent": "none",
        "publishTime": "2022-06-26T19:51:54Z"
      }
    },
    {
      "kind": "youtube#searchResult",
      "etag": "ahylg_xIulLPdlIND1A590vP6J0",
      "id": {
        "kind": "youtube#video",
        "videoId": "ngaT0jlj1wE"
      },
      "snippet": {
        "publishedAt": "2022-06-26T11:49:55Z",
        "channelId": "UC2MGuhIaOP6YLpUx106kTQw",
        "title": "Lead semi-finals highlights || Innsbruck 2022",
        "description": "The sixth stage of the International Federation of Sport Climbing (IFSC) World Cup Series 2022 will see the Boulder and Lead ...",
        "thumbnails": {
          "default": {
            "url": "https://i.ytimg.com/vi/ngaT0jlj1wE/default.jpg",
            "width": 120,
            "height": 90
          },
          "medium": {
            "url": "https://i.ytimg.com/vi/ngaT0jlj1wE/mqdefault.jpg",
            "width": 320,
            "height": 180
          },
          "high": {
            "url": "https://i.ytimg.com/vi/ngaT0jlj1wE/hqdefault.jpg",
            "width": 480,
            "height": 360
          }
        },
        "channelTitle": "International Federation of Sport Climbing",
        "liveBroadcastContent": "none",
        "publishTime": "2022-06-26T11:49:55Z"
      }
    },
    {
      "kind": "youtube#searchResult",
      "etag": "9OzQrL-oZh46z8rvLfrpcMLoWYk",
      "id": {
        "kind": "youtube#video",
        "videoId": "fTxZffkH6Do"
      },
      "snippet": {
        "publishedAt": "2022-06-25T20:19:20Z",
        "channelId": "UC2MGuhIaOP6YLpUx106kTQw",
        "title": "Lead semi-finals || Innsbruck 2022",
        "description": "The Boulder and Lead seasons will cross-paths at the Kletterzentrum Innsbruck, where the sixth stage of the IFSC World Cup ...",
        "thumbnails": {
          "default": {
            "url": "https://i.ytimg.com/vi/fTxZffkH6Do/default.jpg",
            "width": 120,
            "height": 90
          },
          "medium": {
            "url": "https://i.ytimg.com/vi/fTxZffkH6Do/mqdefault.jpg",
            "width": 320,
            "height": 180
          },
          "high": {
            "url": "https://i.ytimg.com/vi/fTxZffkH6Do/hqdefault.jpg",
            "width": 480,
            "height": 360
          }
        },
        "channelTitle": "International Federation of Sport Climbing",
        "liveBroadcastContent": "none",
        "publishTime": "2022-06-25T20:19:20Z"
      }
    },
    {
      "kind": "youtube#searchResult",
      "etag": "w_lt0BTrczSxcLd0gmABYrbJkHY",
      "id": {
        "kind": "youtube#video",
        "videoId": "EVbBDKG2dug"
      },
      "snippet": {
        "publishedAt": "2022-06-25T08:40:56Z",
        "channelId": "UC2MGuhIaOP6YLpUx106kTQw",
        "title": "Women&#39;s Boulder final highlights || Innsbruck 2022",
        "description": "The sixth stage of the International Federation of Sport Climbing (IFSC) World Cup Series 2022 will see the Boulder and Lead ...",
        "thumbnails": {
          "default": {
            "url": "https://i.ytimg.com/vi/EVbBDKG2dug/default.jpg",
            "width": 120,
            "height": 90
          },
          "medium": {
            "url": "https://i.ytimg.com/vi/EVbBDKG2dug/mqdefault.jpg",
            "width": 320,
            "height": 180
          },
          "high": {
            "url": "https://i.ytimg.com/vi/EVbBDKG2dug/hqdefault.jpg",
            "width": 480,
            "height": 360
          }
        },
        "channelTitle": "International Federation of Sport Climbing",
        "liveBroadcastContent": "none",
        "publishTime": "2022-06-25T08:40:56Z"
      }
    },
    {
      "kind": "youtube#searchResult",
      "etag": "jEHczq0N5pnq0ROVGfpKxbiG1pg",
      "id": {
        "kind": "youtube#video",
        "videoId": "kgNU7dbbv10"
      },
      "snippet": {
        "publishedAt": "2022-06-24T20:31:17Z",
        "channelId": "UC2MGuhIaOP6YLpUx106kTQw",
        "title": "Women&#39;s Boulder final || Innsbruck 2022",
        "description": "The Boulder and Lead seasons will cross-paths at the Kletterzentrum Innsbruck, where the sixth stage of the IFSC World Cup ...",
        "thumbnails": {
          "default": {
            "url": "https://i.ytimg.com/vi/kgNU7dbbv10/default.jpg",
            "width": 120,
            "height": 90
          },
          "medium": {
            "url": "https://i.ytimg.com/vi/kgNU7dbbv10/mqdefault.jpg",
            "width": 320,
            "height": 180
          },
          "high": {
            "url": "https://i.ytimg.com/vi/kgNU7dbbv10/hqdefault.jpg",
            "width": 480,
            "height": 360
          }
        },
        "channelTitle": "International Federation of Sport Climbing",
        "liveBroadcastContent": "none",
        "publishTime": "2022-06-24T20:31:17Z"
      }
    },
    {
      "kind": "youtube#searchResult",
      "etag": "OLCbKSfayy3xP34-6vPoKUkcaKs",
      "id": {
        "kind": "youtube#video",
        "videoId": "wsdLCl4CGXc"
      },
      "snippet": {
        "publishedAt": "2022-06-24T13:55:34Z",
        "channelId": "UC2MGuhIaOP6YLpUx106kTQw",
        "title": "Women&#39;s Boulder semi-final || Innsbruck 2022",
        "description": "The Boulder and Lead seasons will cross-paths at the Kletterzentrum Innsbruck, where the sixth stage of the IFSC World Cup ...",
        "thumbnails": {
          "default": {
            "url": "https://i.ytimg.com/vi/wsdLCl4CGXc/default.jpg",
            "width": 120,
            "height": 90
          },
          "medium": {
            "url": "https://i.ytimg.com/vi/wsdLCl4CGXc/mqdefault.jpg",
            "width": 320,
            "height": 180
          },
          "high": {
            "url": "https://i.ytimg.com/vi/wsdLCl4CGXc/hqdefault.jpg",
            "width": 480,
            "height": 360
          }
        },
        "channelTitle": "International Federation of Sport Climbing",
        "liveBroadcastContent": "none",
        "publishTime": "2022-06-24T13:55:34Z"
      }
    },
    {
      "kind": "youtube#searchResult",
      "etag": "9C6hFPWtv7H6YSU77jRLZWWTYyc",
      "id": {
        "kind": "youtube#video",
        "videoId": "G7P_nSsa1EY"
      },
      "snippet": {
        "publishedAt": "2022-06-24T10:14:33Z",
        "channelId": "UC2MGuhIaOP6YLpUx106kTQw",
        "title": "Men&#39;s Boulder final highlights || Innsbruck 2022",
        "description": "The sixth stage of the International Federation of Sport Climbing (IFSC) World Cup Series 2022 will see the Boulder and Lead ...",
        "thumbnails": {
          "default": {
            "url": "https://i.ytimg.com/vi/G7P_nSsa1EY/default.jpg",
            "width": 120,
            "height": 90
          },
          "medium": {
            "url": "https://i.ytimg.com/vi/G7P_nSsa1EY/mqdefault.jpg",
            "width": 320,
            "height": 180
          },
          "high": {
            "url": "https://i.ytimg.com/vi/G7P_nSsa1EY/hqdefault.jpg",
            "width": 480,
            "height": 360
          }
        },
        "channelTitle": "International Federation of Sport Climbing",
        "liveBroadcastContent": "none",
        "publishTime": "2022-06-24T10:14:33Z"
      }
    },
    {
      "kind": "youtube#searchResult",
      "etag": "o4A2szgtTVYfryp4ri4AH5qyxkA",
      "id": {
        "kind": "youtube#video",
        "videoId": "f1vh5p5jsoA"
      },
      "snippet": {
        "publishedAt": "2022-06-23T20:08:57Z",
        "channelId": "UC2MGuhIaOP6YLpUx106kTQw",
        "title": "Men&#39;s Boulder final || Innsbruck 2022",
        "description": "The Boulder and Lead seasons will cross-paths at the Kletterzentrum Innsbruck, where the sixth stage of the IFSC World Cup ...",
        "thumbnails": {
          "default": {
            "url": "https://i.ytimg.com/vi/f1vh5p5jsoA/default.jpg",
            "width": 120,
            "height": 90
          },
          "medium": {
            "url": "https://i.ytimg.com/vi/f1vh5p5jsoA/mqdefault.jpg",
            "width": 320,
            "height": 180
          },
          "high": {
            "url": "https://i.ytimg.com/vi/f1vh5p5jsoA/hqdefault.jpg",
            "width": 480,
            "height": 360
          }
        },
        "channelTitle": "International Federation of Sport Climbing",
        "liveBroadcastContent": "none",
        "publishTime": "2022-06-23T20:08:57Z"
      }
    },
    {
      "kind": "youtube#searchResult",
      "etag": "D9GU08dgm4Ehz3GvmuhYZWb0OVs",
      "id": {
        "kind": "youtube#video",
        "videoId": "ER8XJClb6aE"
      },
      "snippet": {
        "publishedAt": "2022-06-23T13:37:31Z",
        "channelId": "UC2MGuhIaOP6YLpUx106kTQw",
        "title": "Men&#39;s Boulder semi-final || Innsbruck 2022",
        "description": "The Boulder and Lead seasons will cross-paths at the Kletterzentrum Innsbruck, where the sixth stage of the IFSC World Cup ...",
        "thumbnails": {
          "default": {
            "url": "https://i.ytimg.com/vi/ER8XJClb6aE/default.jpg",
            "width": 120,
            "height": 90
          },
          "medium": {
            "url": "https://i.ytimg.com/vi/ER8XJClb6aE/mqdefault.jpg",
            "width": 320,
            "height": 180
          },
          "high": {
            "url": "https://i.ytimg.com/vi/ER8XJClb6aE/hqdefault.jpg",
            "width": 480,
            "height": 360
          }
        },
        "channelTitle": "International Federation of Sport Climbing",
        "liveBroadcastContent": "none",
        "publishTime": "2022-06-23T13:37:31Z"
      }
    },
    {
      "kind": "youtube#searchResult",
      "etag": "V2wqtZD0OxTZPrAnkVDduFkX7Ac",
      "id": {
        "kind": "youtube#video",
        "videoId": "gQJPNkUST3I"
      },
      "snippet": {
        "publishedAt": "2022-06-23T08:00:01Z",
        "channelId": "UC2MGuhIaOP6YLpUx106kTQw",
        "title": "Boulder qualifications highlights || Innsbruck 2022",
        "description": "The Boulder and Lead seasons will cross-paths at the Kletterzentrum Innsbruck, where the sixth stage of the IFSC World Cup ...",
        "thumbnails": {
          "default": {
            "url": "https://i.ytimg.com/vi/gQJPNkUST3I/default.jpg",
            "width": 120,
            "height": 90
          },
          "medium": {
            "url": "https://i.ytimg.com/vi/gQJPNkUST3I/mqdefault.jpg",
            "width": 320,
            "height": 180
          },
          "high": {
            "url": "https://i.ytimg.com/vi/gQJPNkUST3I/hqdefault.jpg",
            "width": 480,
            "height": 360
          }
        },
        "channelTitle": "International Federation of Sport Climbing",
        "liveBroadcastContent": "none",
        "publishTime": "2022-06-23T08:00:01Z"
      }
    },
    {
      "kind": "youtube#searchResult",
      "etag": "ElKbX40kYXM2OaIlimiyRLh9xKw",
      "id": {
        "kind": "youtube#video",
        "videoId": "upWiOpkYPIg"
      },
      "snippet": {
        "publishedAt": "2022-06-23T07:00:08Z",
        "channelId": "UC2MGuhIaOP6YLpUx106kTQw",
        "title": "Paraclimbing finals highlights || Innsbruck 2022",
        "description": "The Boulder and Lead seasons will cross-paths at the Kletterzentrum Innsbruck, where the sixth stage of the IFSC World Cup ...",
        "thumbnails": {
          "default": {
            "url": "https://i.ytimg.com/vi/upWiOpkYPIg/default.jpg",
            "width": 120,
            "height": 90
          },
          "medium": {
            "url": "https://i.ytimg.com/vi/upWiOpkYPIg/mqdefault.jpg",
            "width": 320,
            "height": 180
          },
          "high": {
            "url": "https://i.ytimg.com/vi/upWiOpkYPIg/hqdefault.jpg",
            "width": 480,
            "height": 360
          }
        },
        "channelTitle": "International Federation of Sport Climbing",
        "liveBroadcastContent": "none",
        "publishTime": "2022-06-23T07:00:08Z"
      }
    },
    {
      "kind": "youtube#searchResult",
      "etag": "O1NpVjw0otbWrBiDlarzEXajodA",
      "id": {
        "kind": "youtube#video",
        "videoId": "xf2iUxx0PuY"
      },
      "snippet": {
        "publishedAt": "2022-06-22T21:31:37Z",
        "channelId": "UC2MGuhIaOP6YLpUx106kTQw",
        "title": "Paraclimbing finals || Innsbruck 2022",
        "description": "The Boulder and Lead seasons will cross-paths at the Kletterzentrum Innsbruck, where the sixth stage of the IFSC World Cup ...",
        "thumbnails": {
          "default": {
            "url": "https://i.ytimg.com/vi/xf2iUxx0PuY/default.jpg",
            "width": 120,
            "height": 90
          },
          "medium": {
            "url": "https://i.ytimg.com/vi/xf2iUxx0PuY/mqdefault.jpg",
            "width": 320,
            "height": 180
          },
          "high": {
            "url": "https://i.ytimg.com/vi/xf2iUxx0PuY/hqdefault.jpg",
            "width": 480,
            "height": 360
          }
        },
        "channelTitle": "International Federation of Sport Climbing",
        "liveBroadcastContent": "none",
        "publishTime": "2022-06-22T21:31:37Z"
      }
    },
    {
      "kind": "youtube#searchResult",
      "etag": "i4leRhQ1poWaMlSR8mm317IjKM8",
      "id": {
        "kind": "youtube#video",
        "videoId": "Z-N1bKzSFZI"
      },
      "snippet": {
        "publishedAt": "2022-06-12T22:59:17Z",
        "channelId": "UC2MGuhIaOP6YLpUx106kTQw",
        "title": "Men&#39;s Boulder final highlights || Brixen 2022",
        "description": "Following back-to-back World Cups last month in Salt Lake City, Utah, USA, the International Federation of Sport Climbing (IFSC) ...",
        "thumbnails": {
          "default": {
            "url": "https://i.ytimg.com/vi/Z-N1bKzSFZI/default.jpg",
            "width": 120,
            "height": 90
          },
          "medium": {
            "url": "https://i.ytimg.com/vi/Z-N1bKzSFZI/mqdefault.jpg",
            "width": 320,
            "height": 180
          },
          "high": {
            "url": "https://i.ytimg.com/vi/Z-N1bKzSFZI/hqdefault.jpg",
            "width": 480,
            "height": 360
          }
        },
        "channelTitle": "International Federation of Sport Climbing",
        "liveBroadcastContent": "none",
        "publishTime": "2022-06-12T22:59:17Z"
      }
    },
    {
      "kind": "youtube#searchResult",
      "etag": "gmUHJOt0H4yjP9wev-qqsFd_Vig",
      "id": {
        "kind": "youtube#video",
        "videoId": "FEdX-flUTzo"
      },
      "snippet": {
        "publishedAt": "2022-06-12T19:17:37Z",
        "channelId": "UC2MGuhIaOP6YLpUx106kTQw",
        "title": "Men&#39;s Boulder final || Brixen 2022",
        "description": "Following back-to-back World Cups last month in Salt Lake City, Utah, USA, the International Federation of Sport Climbing (IFSC) ...",
        "thumbnails": {
          "default": {
            "url": "https://i.ytimg.com/vi/FEdX-flUTzo/default.jpg",
            "width": 120,
            "height": 90
          },
          "medium": {
            "url": "https://i.ytimg.com/vi/FEdX-flUTzo/mqdefault.jpg",
            "width": 320,
            "height": 180
          },
          "high": {
            "url": "https://i.ytimg.com/vi/FEdX-flUTzo/hqdefault.jpg",
            "width": 480,
            "height": 360
          }
        },
        "channelTitle": "International Federation of Sport Climbing",
        "liveBroadcastContent": "none",
        "publishTime": "2022-06-12T19:17:37Z"
      }
    },
    {
      "kind": "youtube#searchResult",
      "etag": "aQ18GUgWRuSZbQOmI8wQCbBmI18",
      "id": {
        "kind": "youtube#video",
        "videoId": "hFyQjF8VBrU"
      },
      "snippet": {
        "publishedAt": "2022-06-12T17:11:50Z",
        "channelId": "UC2MGuhIaOP6YLpUx106kTQw",
        "title": "Women&#39;s Boulder final highlights || Brixen 2022",
        "description": "Following back-to-back World Cups last month in Salt Lake City, Utah, USA, the International Federation of Sport Climbing (IFSC) ...",
        "thumbnails": {
          "default": {
            "url": "https://i.ytimg.com/vi/hFyQjF8VBrU/default.jpg",
            "width": 120,
            "height": 90
          },
          "medium": {
            "url": "https://i.ytimg.com/vi/hFyQjF8VBrU/mqdefault.jpg",
            "width": 320,
            "height": 180
          },
          "high": {
            "url": "https://i.ytimg.com/vi/hFyQjF8VBrU/hqdefault.jpg",
            "width": 480,
            "height": 360
          }
        },
        "channelTitle": "International Federation of Sport Climbing",
        "liveBroadcastContent": "none",
        "publishTime": "2022-06-12T17:11:50Z"
      }
    },
    {
      "kind": "youtube#searchResult",
      "etag": "EeF7OamNF1dVvU6g_rv96T1UcmM",
      "id": {
        "kind": "youtube#video",
        "videoId": "z3oeiEMbfIs"
      },
      "snippet": {
        "publishedAt": "2022-06-12T11:32:28Z",
        "channelId": "UC2MGuhIaOP6YLpUx106kTQw",
        "title": "Men&#39;s Boulder semi-final || Brixen 2022",
        "description": "Following back-to-back World Cups last month in Salt Lake City, Utah, USA, the International Federation of Sport Climbing (IFSC) ...",
        "thumbnails": {
          "default": {
            "url": "https://i.ytimg.com/vi/z3oeiEMbfIs/default.jpg",
            "width": 120,
            "height": 90
          },
          "medium": {
            "url": "https://i.ytimg.com/vi/z3oeiEMbfIs/mqdefault.jpg",
            "width": 320,
            "height": 180
          },
          "high": {
            "url": "https://i.ytimg.com/vi/z3oeiEMbfIs/hqdefault.jpg",
            "width": 480,
            "height": 360
          }
        },
        "channelTitle": "International Federation of Sport Climbing",
        "liveBroadcastContent": "none",
        "publishTime": "2022-06-12T11:32:28Z"
      }
    },
    {
      "kind": "youtube#searchResult",
      "etag": "m7xF-BldKQRlN9HODTzONkF6W_k",
      "id": {
        "kind": "youtube#video",
        "videoId": "RawUlgl-DoA"
      },
      "snippet": {
        "publishedAt": "2022-06-12T09:21:50Z",
        "channelId": "UC2MGuhIaOP6YLpUx106kTQw",
        "title": "Hannah Meul 🇩🇪 pulls a figure-4 out of her bag of tricks!",
        "description": "",
        "thumbnails": {
          "default": {
            "url": "https://i.ytimg.com/vi/RawUlgl-DoA/default.jpg",
            "width": 120,
            "height": 90
          },
          "medium": {
            "url": "https://i.ytimg.com/vi/RawUlgl-DoA/mqdefault.jpg",
            "width": 320,
            "height": 180
          },
          "high": {
            "url": "https://i.ytimg.com/vi/RawUlgl-DoA/hqdefault.jpg",
            "width": 480,
            "height": 360
          }
        },
        "channelTitle": "International Federation of Sport Climbing",
        "liveBroadcastContent": "none",
        "publishTime": "2022-06-12T09:21:50Z"
      }
    },
    {
      "kind": "youtube#searchResult",
      "etag": "kjT7-OOtPfNwkhc9Paxsis62rx4",
      "id": {
        "kind": "youtube#video",
        "videoId": "WsE34CKp1A8"
      },
      "snippet": {
        "publishedAt": "2022-06-11T20:06:44Z",
        "channelId": "UC2MGuhIaOP6YLpUx106kTQw",
        "title": "Women&#39;s Boulder final || Brixen 2022",
        "description": "Following back-to-back World Cups last month in Salt Lake City, Utah, USA, the International Federation of Sport Climbing (IFSC) ...",
        "thumbnails": {
          "default": {
            "url": "https://i.ytimg.com/vi/WsE34CKp1A8/default.jpg",
            "width": 120,
            "height": 90
          },
          "medium": {
            "url": "https://i.ytimg.com/vi/WsE34CKp1A8/mqdefault.jpg",
            "width": 320,
            "height": 180
          },
          "high": {
            "url": "https://i.ytimg.com/vi/WsE34CKp1A8/hqdefault.jpg",
            "width": 480,
            "height": 360
          }
        },
        "channelTitle": "International Federation of Sport Climbing",
        "liveBroadcastContent": "none",
        "publishTime": "2022-06-11T20:06:44Z"
      }
    },
    {
      "kind": "youtube#searchResult",
      "etag": "DEAVS0YxRNYQxRUXmuxUuRhRWHE",
      "id": {
        "kind": "youtube#video",
        "videoId": "8Q2yKkFY2Wc"
      },
      "snippet": {
        "publishedAt": "2022-06-11T11:31:11Z",
        "channelId": "UC2MGuhIaOP6YLpUx106kTQw",
        "title": "Women&#39;s Boulder semi-final || Brixen 2022",
        "description": "Following back-to-back World Cups last month in Salt Lake City, Utah, USA, the International Federation of Sport Climbing (IFSC) ...",
        "thumbnails": {
          "default": {
            "url": "https://i.ytimg.com/vi/8Q2yKkFY2Wc/default.jpg",
            "width": 120,
            "height": 90
          },
          "medium": {
            "url": "https://i.ytimg.com/vi/8Q2yKkFY2Wc/mqdefault.jpg",
            "width": 320,
            "height": 180
          },
          "high": {
            "url": "https://i.ytimg.com/vi/8Q2yKkFY2Wc/hqdefault.jpg",
            "width": 480,
            "height": 360
          }
        },
        "channelTitle": "International Federation of Sport Climbing",
        "liveBroadcastContent": "none",
        "publishTime": "2022-06-11T11:31:11Z"
      }
    },
    {
      "kind": "youtube#searchResult",
      "etag": "bOQdiT0uowvv_N-moTZGiHV5Bek",
      "id": {
        "kind": "youtube#video",
        "videoId": "__ym5-pfvtM"
      },
      "snippet": {
        "publishedAt": "2022-06-11T07:08:51Z",
        "channelId": "UC2MGuhIaOP6YLpUx106kTQw",
        "title": "Boulder qualifications highlights || Brixen 2022",
        "description": "Following back-to-back World Cups last month in Salt Lake City, Utah, USA, the International Federation of Sport Climbing (IFSC) ...",
        "thumbnails": {
          "default": {
            "url": "https://i.ytimg.com/vi/__ym5-pfvtM/default.jpg",
            "width": 120,
            "height": 90
          },
          "medium": {
            "url": "https://i.ytimg.com/vi/__ym5-pfvtM/mqdefault.jpg",
            "width": 320,
            "height": 180
          },
          "high": {
            "url": "https://i.ytimg.com/vi/__ym5-pfvtM/hqdefault.jpg",
            "width": 480,
            "height": 360
          }
        },
        "channelTitle": "International Federation of Sport Climbing",
        "liveBroadcastContent": "none",
        "publishTime": "2022-06-11T07:08:51Z"
      }
    },
    {
      "kind": "youtube#searchResult",
      "etag": "rW1cIhuvh0YlvR32F_u8X2lIpNA",
      "id": {
        "kind": "youtube#video",
        "videoId": "MQbiU2OtZ9o"
      },
      "snippet": {
        "publishedAt": "2022-05-30T16:10:54Z",
        "channelId": "UC2MGuhIaOP6YLpUx106kTQw",
        "title": "Boulder finals highlights || Salt Lake City 2022",
        "description": "The International Federation of Sport Climbing (IFSC) World Cup Series 2022 kicked off at the beginning of April, in Meiringen, ...",
        "thumbnails": {
          "default": {
            "url": "https://i.ytimg.com/vi/MQbiU2OtZ9o/default.jpg",
            "width": 120,
            "height": 90
          },
          "medium": {
            "url": "https://i.ytimg.com/vi/MQbiU2OtZ9o/mqdefault.jpg",
            "width": 320,
            "height": 180
          },
          "high": {
            "url": "https://i.ytimg.com/vi/MQbiU2OtZ9o/hqdefault.jpg",
            "width": 480,
            "height": 360
          }
        },
        "channelTitle": "International Federation of Sport Climbing",
        "liveBroadcastContent": "none",
        "publishTime": "2022-05-30T16:10:54Z"
      }
    },
    {
      "kind": "youtube#searchResult",
      "etag": "R9sw6aP1LNphamkTTXaMwgVkNnk",
      "id": {
        "kind": "youtube#video",
        "videoId": "LyVo8LMuUMo"
      },
      "snippet": {
        "publishedAt": "2022-05-30T03:40:20Z",
        "channelId": "UC2MGuhIaOP6YLpUx106kTQw",
        "title": "Boulder finals || Salt Lake City 2022",
        "description": "The International Federation of Sport Climbing (IFSC) World Cup Series 2022 kicked off at the beginning of April, in Meiringen, ...",
        "thumbnails": {
          "default": {
            "url": "https://i.ytimg.com/vi/LyVo8LMuUMo/default.jpg",
            "width": 120,
            "height": 90
          },
          "medium": {
            "url": "https://i.ytimg.com/vi/LyVo8LMuUMo/mqdefault.jpg",
            "width": 320,
            "height": 180
          },
          "high": {
            "url": "https://i.ytimg.com/vi/LyVo8LMuUMo/hqdefault.jpg",
            "width": 480,
            "height": 360
          }
        },
        "channelTitle": "International Federation of Sport Climbing",
        "liveBroadcastContent": "none",
        "publishTime": "2022-05-30T03:40:20Z"
      }
    },
    {
      "kind": "youtube#searchResult",
      "etag": "2BDJTtQ_ywFBkW6wJnhVEIYMz9w",
      "id": {
        "kind": "youtube#video",
        "videoId": "F7l1P2tInQc"
      },
      "snippet": {
        "publishedAt": "2022-05-29T19:31:56Z",
        "channelId": "UC2MGuhIaOP6YLpUx106kTQw",
        "title": "Boulder semi-finals || Salt Lake City 2022",
        "description": "The International Federation of Sport Climbing (IFSC) World Cup Series 2022 kicked off at the beginning of April, in Meiringen, ...",
        "thumbnails": {
          "default": {
            "url": "https://i.ytimg.com/vi/F7l1P2tInQc/default.jpg",
            "width": 120,
            "height": 90
          },
          "medium": {
            "url": "https://i.ytimg.com/vi/F7l1P2tInQc/mqdefault.jpg",
            "width": 320,
            "height": 180
          },
          "high": {
            "url": "https://i.ytimg.com/vi/F7l1P2tInQc/hqdefault.jpg",
            "width": 480,
            "height": 360
          }
        },
        "channelTitle": "International Federation of Sport Climbing",
        "liveBroadcastContent": "none",
        "publishTime": "2022-05-29T19:31:56Z"
      }
    },
    {
      "kind": "youtube#searchResult",
      "etag": "UlSt1WI-d3123zhYLXdGYygDcn0",
      "id": {
        "kind": "youtube#video",
        "videoId": "UkmIgE6iWAs"
      },
      "snippet": {
        "publishedAt": "2022-05-29T05:03:48Z",
        "channelId": "UC2MGuhIaOP6YLpUx106kTQw",
        "title": "Boulder qualifications highlights || Salt Lake City 2022",
        "description": "The International Federation of Sport Climbing (IFSC) World Cup Series 2022 kicked off at the beginning of April, in Meiringen, ...",
        "thumbnails": {
          "default": {
            "url": "https://i.ytimg.com/vi/UkmIgE6iWAs/default.jpg",
            "width": 120,
            "height": 90
          },
          "medium": {
            "url": "https://i.ytimg.com/vi/UkmIgE6iWAs/mqdefault.jpg",
            "width": 320,
            "height": 180
          },
          "high": {
            "url": "https://i.ytimg.com/vi/UkmIgE6iWAs/hqdefault.jpg",
            "width": 480,
            "height": 360
          }
        },
        "channelTitle": "International Federation of Sport Climbing",
        "liveBroadcastContent": "none",
        "publishTime": "2022-05-29T05:03:48Z"
      }
    },
    {
      "kind": "youtube#searchResult",
      "etag": "nfGwgqA9gvrXFOCDMKv99WEqWOY",
      "id": {
        "kind": "youtube#video",
        "videoId": "E1LZzlVzV14"
      },
      "snippet": {
        "publishedAt": "2022-05-28T09:22:02Z",
        "channelId": "UC2MGuhIaOP6YLpUx106kTQw",
        "title": "Speed finals highlights || Salt Lake City 2022",
        "description": "The International Federation of Sport Climbing (IFSC) World Cup Series 2022 kicked off at the beginning of April, in Meiringen, ...",
        "thumbnails": {
          "default": {
            "url": "https://i.ytimg.com/vi/E1LZzlVzV14/default.jpg",
            "width": 120,
            "height": 90
          },
          "medium": {
            "url": "https://i.ytimg.com/vi/E1LZzlVzV14/mqdefault.jpg",
            "width": 320,
            "height": 180
          },
          "high": {
            "url": "https://i.ytimg.com/vi/E1LZzlVzV14/hqdefault.jpg",
            "width": 480,
            "height": 360
          }
        },
        "channelTitle": "International Federation of Sport Climbing",
        "liveBroadcastContent": "none",
        "publishTime": "2022-05-28T09:22:02Z"
      }
    },
    {
      "kind": "youtube#searchResult",
      "etag": "WAi2NUfrzVN48bb7vpjXi3faThQ",
      "id": {
        "kind": "youtube#video",
        "videoId": "ilKcezCgwAU"
      },
      "snippet": {
        "publishedAt": "2022-05-28T03:23:06Z",
        "channelId": "UC2MGuhIaOP6YLpUx106kTQw",
        "title": "Speed finals || Salt Lake City 2022",
        "description": "The International Federation of Sport Climbing (IFSC) World Cup Series 2022 kicked off at the beginning of April, in Meiringen, ...",
        "thumbnails": {
          "default": {
            "url": "https://i.ytimg.com/vi/ilKcezCgwAU/default.jpg",
            "width": 120,
            "height": 90
          },
          "medium": {
            "url": "https://i.ytimg.com/vi/ilKcezCgwAU/mqdefault.jpg",
            "width": 320,
            "height": 180
          },
          "high": {
            "url": "https://i.ytimg.com/vi/ilKcezCgwAU/hqdefault.jpg",
            "width": 480,
            "height": 360
          }
        },
        "channelTitle": "International Federation of Sport Climbing",
        "liveBroadcastContent": "none",
        "publishTime": "2022-05-28T03:23:06Z"
      }
    },
    {
      "kind": "youtube#searchResult",
      "etag": "XWC7tHktHjRQ17s7axyH9sGNYUM",
      "id": {
        "kind": "youtube#video",
        "videoId": "11IrXLhYVNs"
      },
      "snippet": {
        "publishedAt": "2022-05-27T16:01:42Z",
        "channelId": "UC2MGuhIaOP6YLpUx106kTQw",
        "title": "Paraclimbing finals highlights || Salt Lake City 2022",
        "description": "The International Federation of Sport Climbing (IFSC) World Cup Series 2022 kicked off at the beginning of April, in Meiringen, ...",
        "thumbnails": {
          "default": {
            "url": "https://i.ytimg.com/vi/11IrXLhYVNs/default.jpg",
            "width": 120,
            "height": 90
          },
          "medium": {
            "url": "https://i.ytimg.com/vi/11IrXLhYVNs/mqdefault.jpg",
            "width": 320,
            "height": 180
          },
          "high": {
            "url": "https://i.ytimg.com/vi/11IrXLhYVNs/hqdefault.jpg",
            "width": 480,
            "height": 360
          }
        },
        "channelTitle": "International Federation of Sport Climbing",
        "liveBroadcastContent": "none",
        "publishTime": "2022-05-27T16:01:42Z"
      }
    },
    {
      "kind": "youtube#searchResult",
      "etag": "7Vvj8my9dDcfSEBoF5yWlZsQRs4",
      "id": {
        "kind": "youtube#video",
        "videoId": "FcycqiBKO-o"
      },
      "snippet": {
        "publishedAt": "2022-05-25T20:55:57Z",
        "channelId": "UC2MGuhIaOP6YLpUx106kTQw",
        "title": "Paraclimbing finals || Salt Lake City 2022",
        "description": "The International Federation of Sport Climbing (IFSC) World Cup Series 2022 kicked off at the beginning of April, in Meiringen, ...",
        "thumbnails": {
          "default": {
            "url": "https://i.ytimg.com/vi/FcycqiBKO-o/default.jpg",
            "width": 120,
            "height": 90
          },
          "medium": {
            "url": "https://i.ytimg.com/vi/FcycqiBKO-o/mqdefault.jpg",
            "width": 320,
            "height": 180
          },
          "high": {
            "url": "https://i.ytimg.com/vi/FcycqiBKO-o/hqdefault.jpg",
            "width": 480,
            "height": 360
          }
        },
        "channelTitle": "International Federation of Sport Climbing",
        "liveBroadcastContent": "none",
        "publishTime": "2022-05-25T20:55:57Z"
      }
    },
    {
      "kind": "youtube#searchResult",
      "etag": "lu-dHr2XWWz4n6adnML7sKfbVe4",
      "id": {
        "kind": "youtube#video",
        "videoId": "wj6PpQvK8ds"
      },
      "snippet": {
        "publishedAt": "2022-05-23T14:41:17Z",
        "channelId": "UC2MGuhIaOP6YLpUx106kTQw",
        "title": "Boulder finals highlights || Salt Lake City 2022",
        "description": "The International Federation of Sport Climbing (IFSC) World Cup Series 2022 kicked off at the beginning of April, in Meiringen, ...",
        "thumbnails": {
          "default": {
            "url": "https://i.ytimg.com/vi/wj6PpQvK8ds/default.jpg",
            "width": 120,
            "height": 90
          },
          "medium": {
            "url": "https://i.ytimg.com/vi/wj6PpQvK8ds/mqdefault.jpg",
            "width": 320,
            "height": 180
          },
          "high": {
            "url": "https://i.ytimg.com/vi/wj6PpQvK8ds/hqdefault.jpg",
            "width": 480,
            "height": 360
          }
        },
        "channelTitle": "International Federation of Sport Climbing",
        "liveBroadcastContent": "none",
        "publishTime": "2022-05-23T14:41:17Z"
      }
    },
    {
      "kind": "youtube#searchResult",
      "etag": "ttiCk-0uUFNbLvcGuL_DPaxOakI",
      "id": {
        "kind": "youtube#video",
        "videoId": "5fC7gSX2ivU"
      },
      "snippet": {
        "publishedAt": "2022-05-23T04:24:21Z",
        "channelId": "UC2MGuhIaOP6YLpUx106kTQw",
        "title": "Boulder finals || Salt Lake City 2022",
        "description": "The International Federation of Sport Climbing (IFSC) World Cup Series 2022 kicked off at the beginning of April, in Meiringen, ...",
        "thumbnails": {
          "default": {
            "url": "https://i.ytimg.com/vi/5fC7gSX2ivU/default.jpg",
            "width": 120,
            "height": 90
          },
          "medium": {
            "url": "https://i.ytimg.com/vi/5fC7gSX2ivU/mqdefault.jpg",
            "width": 320,
            "height": 180
          },
          "high": {
            "url": "https://i.ytimg.com/vi/5fC7gSX2ivU/hqdefault.jpg",
            "width": 480,
            "height": 360
          }
        },
        "channelTitle": "International Federation of Sport Climbing",
        "liveBroadcastContent": "none",
        "publishTime": "2022-05-23T04:24:21Z"
      }
    }
  ]
}
