{
  "kind": "youtube#videoListResponse",
  "etag": "SURIGuOet3H-ZiqtZ0Rj6E6M9_c",
  "items": [
    {
      "kind": "youtube#video",
      "etag": "1ktbzq31G-UQ-WXcQJL9Kv93H30",
      "id": "5EZI7Az1OOE",
      "contentDetails": {
        "duration": "PT1M6S",
        "dimension": "2d",
        "definition": "hd",
        "caption": "false",
        "licensedContent": true,
        "contentRating": {},
        "projection": "rectangular"
      }
    }
  ],
  "pageInfo": {
    "totalResults": 1,
    "resultsPerPage": 1
  }
}
