{
  "kind": "youtube#videoListResponse",
  "etag": "xMBnLfEcSdpL-V_eyIRgih61_Js",
  "items": [
    {
      "kind": "youtube#video",
      "etag": "j0I60zgXshIukOypnj-v-8z32us",
      "id": "H6TXtxe26-Q",
      "contentDetails": {
        "duration": "PT2H26M11S",
        "dimension": "2d",
        "definition": "hd",
        "caption": "false",
        "licensedContent": true,
        "contentRating": {},
        "projection": "rectangular"
      },
      "liveStreamingDetails": {
        "actualStartTime": "2024-08-27T10:55:36Z",
        "actualEndTime": "2024-08-27T19:31:04Z",
        "scheduledStartTime": "2024-08-27T10:55:00Z"
      }
    }
  ],
  "pageInfo": {
    "totalResults": 1,
    "resultsPerPage": 1
  }
}
