{
  "kind": "youtube#videoListResponse",
  "etag": "YBoBiDEvCyc41H4LwrKAhR-f5TQ",
  "items": [
    {
      "kind": "youtube#video",
      "etag": "CeiVpP5TLR9PywFAAz8toxclcUw",
      "id": "P0giS3XPj_w",
      "contentDetails": {
        "duration": "PT52S",
        "dimension": "2d",
        "definition": "hd",
        "caption": "false",
        "licensedContent": true,
        "contentRating": {},
        "projection": "rectangular"
      }
    }
  ],
  "pageInfo": {
    "totalResults": 1,
    "resultsPerPage": 1
  }
}
