{
  "kind": "youtube#videoListResponse",
  "etag": "v1jxIWG-50pM94nYdw2qsqQuSA8",
  "items": [
    {
      "kind": "youtube#video",
      "etag": "fAhYtGZGrjO7yXTABIzmcPtyeUE",
      "id": "SA18mEBGT5E",
      "contentDetails": {
        "duration": "PT6M27S",
        "dimension": "2d",
        "definition": "hd",
        "caption": "false",
        "licensedContent": false,
        "contentRating": {},
        "projection": "rectangular"
      }
    }
  ],
  "pageInfo": {
    "totalResults": 1,
    "resultsPerPage": 1
  }
}
