{
  "kind": "youtube#videoListResponse",
  "etag": "Myl38kymrjWx8vVFYwofzFY8jz4",
  "items": [
    {
      "kind": "youtube#video",
      "etag": "vCHBZHc8hhXsTTuZivbqqpJ_CRw",
      "id": "X8ClIi_BJIg",
      "contentDetails": {
        "duration": "P0D",
        "dimension": "2d",
        "definition": "sd",
        "caption": "false",
        "licensedContent": true,
        "contentRating": {},
        "projection": "rectangular"
      },
      "liveStreamingDetails": {
        "actualStartTime": "2026-07-21T18:28:26Z",
        "scheduledStartTime": "2026-07-21T18:30:00Z",
        "concurrentViewers": "1180"
      }
    }
  ],
  "pageInfo": {
    "totalResults": 1,
    "resultsPerPage": 1
  }
}
